Workbook

Sheet CONFINAMENTO-MILHO
A1: IRRIGAÇÃP SETOR 1 | D1: ADUBO | H1: APURAÇÃO | M1: MAQUINARIO-ADUBAÇÃO-PLANTIO--CAPINA | S1: VENENO
A2: DATA | B2: MINUTOS | D2: DESCRIÇÃO | E2: DATA | F2: QUANT | H2: DESCRIÇÃO | I2: TOTAL | J2: VALOR COMPRA | K2: CUSTO USADO | M2: DESCRIÇÃO | N2: DATA | O2: QUANT | P2: VALOR | Q2: TOTAL | S2: DESCRIÇÃO | T2: DATA | U2: QUANT | V2: VALOR | W2: TOTAL
A3: 45643 | B3: 160 | D3: SEMENTE DE MILHO BIOMATRIX 3066 | E3: 45527 | F3: 8 | H3: ABADIN 72 EC - 1 LITRO | I3: =SUMIF('CONFINAMENTO-MILHO'!D3:D243,"ABADIN 72 EC - 1 LITRO",'CONFINAMENTO-MILHO'!F3:F243) -> 0 | J3: =COMPRAS!M3 -> 0.13 | K3: =I3*J3 -> 0 | M3: DIARIA MAIKO | N3: 45654 | O3: 1 | P3: 75 | Q3: =O3*P3 -> 75 | S3: LUIZ | T3: 45654 | U3: 4 | V3: 10 | W3: =U3*V3 -> 40
A4: 45644 | B4: 190 | D4: ROUNDUP ORIGINAL MAIS - GL DE 5 L | E4: 45654 | F4: 800 | H4: ABAMEX -1 LITRO | I4: =SUMIF('CONFINAMENTO-MILHO'!D3:D244,"ABAMEX -1 LITRO",'CONFINAMENTO-MILHO'!F3:F244) -> 0 | J4: =COMPRAS!M4 -> 0.05 | K4: =I4*J4 -> 0 | M4: GRADEAÇÃO | O4: 1 | P4: 231 | Q4: =O4*P4 -> 231 | S4: LUIZ | T4: 45660 | U4: 4 | V4: 10 | W4: =U4*V4 -> 40
A5: 45645 | B5: 200 | D5: BRIT | E5: 45654 | F5: 80 | H5: ABAMEX MAXX 72% 12X1 LT | I5: =SUMIF('CONFINAMENTO-MILHO'!D3:D244,"ABAMEX MAXX 72% 12X1 LT",'CONFINAMENTO-MILHO'!F3:F244) -> 0 | J5: =COMPRAS!M5 -> 0.1 | K5: =I5*J5 -> 0 | M5: PLANTIO E REPLANTIO | O5: 3 | P5: 80 | Q5: =U5*P5 -> 320 | S5: LUIZ | T5: 45664 | U5: 4 | V5: 10 | W5: =U5*V5 -> 40
A6: 45646 | B6: 200 | D6: UREIA | E6: 45659 | F6: 72 | H6: ACIDO BORICO SACO 25K | I6: =SUMIF('CONFINAMENTO-MILHO'!D3:D222,"ACIDO BORICO SECO 25K ",'CONFINAMENTO-MILHO'!F3:F222) -> 0 | J6: =COMPRAS!M6 -> 10.2 | K6: =I6*J6 -> 0 | M6: MONTAGEM SISTEMA | O6: 1 | P6: 80 | Q6: =O6*P6 -> 80 | R6: LUIZ | S6: LUIZ | T6: 45675 | U6: 4 | V6: 10 | W6: =U6*V6 -> 40
A7: 45647 | B7: 220 | D7: PIRATE 1 LITRO | E7: 45660 | F7: 160 | H7: ADESIL - 1 LITRO | I7: =SUMIF('CONFINAMENTO-MILHO'!D3:D222,"ADESIL - 1 LITRO ",'CONFINAMENTO-MILHO'!F3:F222) -> 0 | J7: =COMPRAS!M7 -> 0.025 | K7: =I7*J7 -> 0 | M7: ETIRADA MANGUIERAS | O7: 1 | P7: 80 | Q7: =O7*P7 -> 80 | S7: LUIZ | T7: 45678 | U7: 6 | V7: 10 | W7: =U7*V7 -> 60
A8: 45648 | B8: 200 | D8: BRIT | E8: 45660 | F8: 80 | H8: AGRUMAX MZ 4X5 KG | I8: =SUMIF('CONFINAMENTO-MILHO'!D3:D222,"AGRUMAX MZ 4X5 KG ",'CONFINAMENTO-MILHO'!F3:F222) -> 0 | J8: =COMPRAS!M8 -> 0.032 | K8: =I8*J8 -> 0 | M8: NIVELAMENTO NUNAO | O8: 1 | P8: 240 | Q8: =O8*P8 -> 240 | S8: LUIZ | T8: 45693 | U8: 2 | V8: 10 | W8: =U8*V8 -> 20
A9: 45649 | B9: 210 | D9: INTREPID240 SC -1 L | E9: 45660 | F9: 120 | H9: AMISTAR TOP 1 L | I9: =SUMIF('CONFINAMENTO-MILHO'!D3:D223,"AMISTAR TOP 1 L",'CONFINAMENTO-MILHO'!F3:F223) -> 0 | J9: =COMPRAS!M9 -> 0.205 | K9: =I9*J9 -> 0 | M9: CUSTO FEITA | O9: 1 | P9: 1050 | Q9: =O9*P9 -> 1050
A10: 45650 | B10: 160 | D10: QUIMIFOL S450 - GL 5 LITROS | E10: 45660 | F10: 120 | H10: AMISTAR WG 6X500 G-1 KILO | I10: =SUMIF('CONFINAMENTO-MILHO'!D3:D223,"AMISTAR WG 6X500 G-1 KILO",'CONFINAMENTO-MILHO'!F3:F223) -> 0 | J10: =COMPRAS!M10 -> 0.2 | K10: =I10*J10 -> 0 | M10: CUSTO SACO | O10: 672 | P10: 1.35 | Q10: =O10*P10 -> 907.2
A11: 45651 | D11: LANNATE | E11: 45664 | F11: 400 | H11: AMPLIGO 250 ML | I11: =SUMIF('CONFINAMENTO-MILHO'!D3:D223,"AMPLIGO 250 ML",'CONFINAMENTO-MILHO'!F3:F223) -> 0 | J11: =COMPRAS!M11 -> 0.39 | K11: =I11*J11 -> 0 | M11: DIARIAS ENSACAR | O11: 14 | P11: 80 | Q11: =O11*P11 -> 1120
A12: 45652 | B12: 180 | D12: INTREPID240 SC -1 L | E12: 45664 | F12: 120 | H12: AVATAR 1 L | I12: =SUMIF('CONFINAMENTO-MILHO'!D3:D243,"AVATAR 1 L",'CONFINAMENTO-MILHO'!F3:F243) -> 0 | J12: =COMPRAS!M12 -> 0.375 | K12: =I12*J12 -> 0 | Q12: =O12*P12 -> 0
A13: 45653 | B13: 180 | D13: RAPEL PCT- 3 KG | E13: 45664 | F13: 480 | H13: BARBANTE EM NOVELO N10 BRANCO | I13: =SUMIF('CONFINAMENTO-MILHO'!D3:D230,"BARBANTE EM NOVELO N10 BRANCO",'CONFINAMENTO-MILHO'!F3:F230) -> 0 | J13: =COMPRAS!M13 -> 29.625 | K13: =I13*J13 -> 0 | Q13: =O13*P13 -> 0
A14: 45654 | B14: 180 | D14: LANNATE | E14: 45675 | F14: 400 | H14: BARBANTE EM NOVELO N8 OURO | I14: =SUMIF('CONFINAMENTO-MILHO'!D3:D229,"BARBANTE EM NOVELO N8 OURO",'CONFINAMENTO-MILHO'!F3:F229) -> 0 | J14: =COMPRAS!M14 -> 31.576923 | K14: =I14*J14 -> 0 | Q14: =O14*P14 -> 0
A15: 45655 | B15: 160 | D15: INTREPID240 SC -1 L | E15: 45675 | F15: 120 | H15: BENZOATO 1K | I15: =SUMIF('CONFINAMENTO-MILHO'!D3:D243,"BENZOATO 1K",'CONFINAMENTO-MILHO'!F3:F243) -> 0 | J15: =COMPRAS!M15 -> 0.45 | K15: =I15*J15 -> 0 | Q15: =O15*P15 -> 0
A16: 45656 | B16: 170 | D16: QUIMIFOL S450 - GL 5 LITROS | E16: 45675 | F16: 240 | H16: BION 500 WG 25 G | I16: =SUMIF('CONFINAMENTO-MILHO'!D3:D222,"BION 500 WG 25 G",'CONFINAMENTO-MILHO'!F3:F222) -> 0 | J16: =COMPRAS!M16 -> 2.8 | K16: =I16*J16 -> 0 | Q16: =O16*P16 -> 0
A17: 45657 | D17: ROUNDUP ORIGINAL MAIS - GL DE 5 L | E17: 45676 | F17: 1500 | H17: BRAVONIL ULTREX 1 KILO | I17: =SUMIF('CONFINAMENTO-MILHO'!D3:D222,"BRAVONIL ULTREX 1 KILO",'CONFINAMENTO-MILHO'!F3:F222) -> 0 | J17: =COMPRAS!M17 -> 0.1 | K17: =I17*J17 -> 0 | Q17: =O17*P17 -> 0
A18: 45658 | D18: UREIA | E18: 45678 | F18: 40 | H18: BRIT | I18: =SUMIF('CONFINAMENTO-MILHO'!D3:D242,"BRIT",'CONFINAMENTO-MILHO'!F3:F242) -> 160 | J18: =COMPRAS!M18 -> 0.065 | K18: =I18*J18 -> 10.4 | Q18: =O18*P18 -> 0
A19: 45659 | D19: SUFATO DE AMONIO | E19: 45678 | F19: 40 | H19: CAIXA PARA TOMATE | I19: =SUMIF('CONFINAMENTO-MILHO'!D3:D222,"CAIXA PARA TOMATE ",'CONFINAMENTO-MILHO'!F3:F222) -> 0 | J19: =COMPRAS!M19 -> 0 | K19: =I19*J19 -> 0 | Q19: =O19*P19 -> 0
A20: 45660 | B20: 80 | D20: NITRATO POTASSIO YARA TERA K 13-00-43 | E20: 45678 | F20: 40 | H20: CAL SUPER 5 LITROS | I20: =SUMIF('CONFINAMENTO-MILHO'!D3:D233,"CAL SUPER 5 LITROS",'CONFINAMENTO-MILHO'!F3:F233) -> 0 | J20: =COMPRAS!M20 -> 0.044 | K20: =I20*J20 -> 0 | Q20: =O20*P20 -> 0
A21: 45661 | B21: 120 | D21: INTREPID240 SC -1 L | E21: 45693 | F21: 60 | H21: CARNADINE- 1 LITRO | I21: =SUMIF('CONFINAMENTO-MILHO'!D3:D247,"CARNADINE- 1 LITRO",'CONFINAMENTO-MILHO'!F3:F247) -> 0 | J21: =COMPRAS!M21 -> 0.060833333 | K21: =I21*J21 -> 0
A22: 45662 | D22: PLATINUM NEO - GL 5 LITROS | E22: 45693 | F22: 60 | H22: CERCOBIN 875 WG- 1 KG | I22: =SUMIF('CONFINAMENTO-MILHO'!D3:D247,"CERCOBIN 875 WG- 1 KG",'CONFINAMENTO-MILHO'!F3:F247) -> 0 | J22: =COMPRAS!M22 -> 0.085 | K22: =I22*J22 -> 0
A23: 45663 | D23: NPK | E23: 45724 | F23: 104 | H23: D FIX - 1 LITRO | I23: =SUMIF('CONFINAMENTO-MILHO'!D3:D243,"D FIX - 1 LITRO",'CONFINAMENTO-MILHO'!F3:F243) -> 0 | J23: =COMPRAS!M23 -> 0.11 | K23: =I23*J23 -> 0
A24: 45664 | B24: 90 | H24: D S30 - 1 LITRO | I24: =SUMIF('CONFINAMENTO-MILHO'!D3:D243,"D S30 - 1 LITRO",'CONFINAMENTO-MILHO'!F3:F243) -> 0 | J24: =COMPRAS!M24 -> 0.065 | K24: =I24*J24 -> 0
A25: 45665 | H25: DELEGATE(TM) - FR 120 GR | I25: =SUMIF('CONFINAMENTO-MILHO'!D3:D243,"DELEGATE(TM) - FR 120 GR",'CONFINAMENTO-MILHO'!F3:F243) -> 0 | J25: =COMPRAS!M25 -> 2.75 | K25: =I25*J25 -> 0
A26: 45666 | H26: DFULL 1 LITRO | I26: =SUMIF('CONFINAMENTO-MILHO'!D3:D243,"DFULL 1 LITRO",'CONFINAMENTO-MILHO'!F3:F243) -> 0 | J26: =COMPRAS!M26 -> 0.155 | K26: =I26*J26 -> 0
A27: 45667 | H27: DICARZOL 500 SP 12 X 500 GRS | I27: =SUMIF('CONFINAMENTO-MILHO'!D3:D243,"DICARZOL 500 SP 12 X 500 GRS",'CONFINAMENTO-MILHO'!F3:F243) -> 0 | J27: =COMPRAS!M27 -> 0.76 | K27: =I27*J27 -> 0
A28: 45668 | H28: DISPAROULTRA-S - GL DE 5 LITROS | I28: =SUMIF('CONFINAMENTO-MILHO'!D3:D243,"DISPAROULTRA-S - GL DE 5 LITROS",'CONFINAMENTO-MILHO'!F3:F243) -> 0 | J28: =COMPRAS!M28 -> 0.028 | K28: =I28*J28 -> 0
A29: 45669 | H29: DOMINUM XT-S - GL 5 LITROS | I29: =SUMIF('CONFINAMENTO-MILHO'!D3:D243,"DOMINUM XT-S - GL 5 LITROS",'CONFINAMENTO-MILHO'!F3:F243) -> 0 | J29: =COMPRAS!M29 -> 0.128 | K29: =I29*J29 -> 0
A30: 45670 | H30: DRIPSOL BORO K 00.00.01+17% BORO 25 k | I30: =SUMIF('CONFINAMENTO-MILHO'!D3:D243,"DRIPSOL BORO K 00.00.01+17% BORO 25 k",'CONFINAMENTO-MILHO'!F3:F243) -> 0 | J30: =COMPRAS!M30 -> 11.4 | K30: =I30*J30 -> 0
A31: 45671 | H31: DRIPSOL CRESCIMENTO 24-10-10 25 KG | I31: =SUMIF('CONFINAMENTO-MILHO'!D3:D238,"DRIPSOL CRESCIMENTO 24-10-10 25 KG",'CONFINAMENTO-MILHO'!F3:F238) -> 0 | J31: =COMPRAS!M31 -> 10.6 | K31: =I31*J31 -> 0
A32: 45672 | H32: DRIPSOL INICIAL 15-30-15 25 KG | I32: =SUMIF('CONFINAMENTO-MILHO'!D3:D222,"DRIPSOL INICIAL 15-30-15 25 KG",'CONFINAMENTO-MILHO'!F3:F222) -> 0 | J32: =COMPRAS!M32 -> 9.2769231 | K32: =I32*J32 -> 0
A33: 45673 | H33: DRIPSOL MICRO REXENE 700 GRAMAS | I33: =SUMIF('CONFINAMENTO-MILHO'!D3:D222,"DRIPSOL MICRO REXENE 700 GRAMAS",'CONFINAMENTO-MILHO'!F3:F222) -> 0 | J33: =COMPRAS!M33 -> 0.082857143 | K33: =I33*J33 -> 0
A34: 45674 | H34: DRIPSOL MULTIPROPOSITO-18-18-18 25 K | I34: =SUMIF('CONFINAMENTO-MILHO'!D3:D222,"DRIPSOL MULTIPROPOSITO-18-18-18 25 K",'CONFINAMENTO-MILHO'!F3:F222) -> 0 | J34: =COMPRAS!M34 -> 10.56 | K34: =I34*J34 -> 0
A35: 45675 | H35: DRIPSOL PRODUÇÃO 12-06-40 25K | I35: =SUMIF('CONFINAMENTO-MILHO'!D3:D236,"DRIPSOL PRODUÇÃO 12-06-40 25K",'CONFINAMENTO-MILHO'!F3:F236) -> 0 | J35: =COMPRAS!M35 -> 11 | K35: =I35*J35 -> 0 | N35: TOTAL | O35: =SUM(O3:O34) -> 695 | Q35: =SUM(Q3:Q34) -> 4103.2 | T35: TOTAL | U35: =SUM(U3:U31) -> 24 | W35: =SUM(W3:W31) -> 240
A36: 45676 | H36: ELEITTO | I36: =SUMIF('CONFINAMENTO-MILHO'!D3:D223,"ELEITTO",'CONFINAMENTO-MILHO'!F3:F223) -> 0 | J36: =COMPRAS!M36 -> 0.33 | K36: =I36*J36 -> 0
A37: 45677 | B37: 131 | H37: FERTIUM LIQUIDO 5L | I37: =SUMIF('CONFINAMENTO-MILHO'!D3:D231,"FERTIUM LIQUIDO 5L",'CONFINAMENTO-MILHO'!F3:F231) -> 0 | J37: =COMPRAS!M37 -> 0.217 | K37: =I37*J37 -> 0
A38: 45678 | B38: 156 | H38: FITILHO VIRGEM NOVELO NR 08 | I38: =SUMIF('CONFINAMENTO-MILHO'!D3:D243,"FITILHO VIRGEM NOVELO NR 08",'CONFINAMENTO-MILHO'!F3:F243) -> 0 | J38: =COMPRAS!M38 -> 40 | K38: =I38*J38 -> 0 | M38: REEMBOLSO DE PAGAMENTO | S38: REEMBOLSO DE PAGAMENTO
A39: 45679 | B39: 155 | H39: FRETE CAIXAS TOMATE | I39: =SUMIF('CONFINAMENTO-MILHO'!D3:D243,"FRETE CAIXAS",'CONFINAMENTO-MILHO'!F3:F243) -> 0 | J39: =COMPRAS!M39 -> 2.3571429 | K39: =I39*J39 -> 0 | M39: REEMBOLSO FERNANDO | N39: =SUMIF('CONFINAMENTO-MILHO'!R1:R30,"R.FERNANDO",'CONFINAMENTO-MILHO'!Q1:Q30) -> 0 | S39: REEMBOLSO FERNANDO | T39: =SUMIF('CONFINAMENTO-MILHO'!X1:X30,"R.FERNANDO",'CONFINAMENTO-MILHO'!W1:W30) -> 0
A40: 45680 | B40: 160 | H40: FTE 25K | I40: =SUMIF('CONFINAMENTO-MILHO'!D3:D241,"FTE 50 KILOS ",'CONFINAMENTO-MILHO'!F3:F241) -> 0 | J40: =COMPRAS!M40 -> 4.4 | K40: =I40*J40 -> 0 | M40: REEMBOLSO RAFAEL | N40: =SUMIF('CONFINAMENTO-MILHO'!R1:R30,"R.RAFAEL",'CONFINAMENTO-MILHO'!Q1:Q30) -> 0 | S40: REEMBOLSO RAFAEL | T40: =SUMIF('CONFINAMENTO-MILHO'!X1:X30,"R.RAFAEL",'CONFINAMENTO-MILHO'!W1:W30) -> 0
A41: 45681 | B41: 160 | H41: FULVUMIM 5 LITROS | I41: =SUMIF('CONFINAMENTO-MILHO'!D3:D222,"FULVUMIM 5 LITROS",'CONFINAMENTO-MILHO'!F3:F222) -> 0 | J41: =COMPRAS!M41 -> 0.025857143 | K41: =I41*J41 -> 0 | M41: REEMBOLSO JEAN | N41: =SUMIF('CONFINAMENTO-MILHO'!R1:R30,"R.JEAN",'CONFINAMENTO-MILHO'!Q1:Q30) -> 0 | S41: REEMBOLSO JEAN | T41: =SUMIF('CONFINAMENTO-MILHO'!X1:X30,"R.JEAN",'CONFINAMENTO-MILHO'!W1:W30) -> 0
A42: 45682 | B42: 110 | H42: FYLLOTON 12X1 1 LITRO | I42: =SUMIF('CONFINAMENTO-MILHO'!D3:D222,"FYLLOTON 12X1 1 LITRO",'CONFINAMENTO-MILHO'!F3:F222) -> 0 | J42: =COMPRAS!M42 -> 0.067222222 | K42: =I42*J42 -> 0
A43: 45683 | B43: 171 | H43: GLIBOR CA 5L | I43: =SUMIF('CONFINAMENTO-MILHO'!D3:D225,"GLIBOR CA 5L",'CONFINAMENTO-MILHO'!F3:F225) -> 0 | J43: =COMPRAS!M43 -> 0.046 | K43: =I43*J43 -> 0
A44: 45684 | B44: 160 | H44: GLIMAN 30 4X5 KG | I44: =SUMIF('CONFINAMENTO-MILHO'!D3:D237,"GLIMAN 30 4X5 KG",'CONFINAMENTO-MILHO'!F3:F237) -> 0 | J44: =COMPRAS!M44 -> 0.04 | K44: =I44*J44 -> 0
A45: 45685 | B45: 161 | H45: INTREPID240 SC -1 L | I45: =SUMIF('CONFINAMENTO-MILHO'!D3:D243,"INTREPID240 SC -1 L",'CONFINAMENTO-MILHO'!F3:F243) -> 420 | J45: =COMPRAS!M45 -> 0.18 | K45: =I45*J45 -> 75.6
A46: 45686 | B46: 160 | H46: JOINER | I46: =SUMIF('CONFINAMENTO-MILHO'!D3:D223,"JOINER",'CONFINAMENTO-MILHO'!F3:F223) -> 0 | J46: =COMPRAS!M46 -> 2.284 | K46: =I46*J46 -> 0 | M46: TOTAL REEMBOLSO
A47: 45687 | B47: 160 | H47: K BOMBER 56 8X2 5 KILOS | I47: =SUMIF('CONFINAMENTO-MILHO'!D3:D243,"K BOMBER 56 8X2 5 KILOS ",'CONFINAMENTO-MILHO'!F3:F243) -> 0 | J47: =COMPRAS!M47 -> 0.024 | K47: =I47*J47 -> 0 | M47: REEMBOLSO FERNANDO | N47: =N39+T39 -> 0
A48: 45688 | B48: 186 | H48: KIT COSTAL AZR PLUS - EPI | I48: =SUMIF('CONFINAMENTO-MILHO'!D3:D243,"KIT COSTAL AZR PLUS - EPI",'CONFINAMENTO-MILHO'!F3:F243) -> 0 | J48: =COMPRAS!M48 -> 110 | K48: =I48*J48 -> 0 | M48: REEMBOLSO RAFAEL | N48: =N40+T40 -> 0
A49: 45689 | B49: 206 | H49: KLORPAN 480 CE -1 LITRO | I49: =SUMIF('CONFINAMENTO-MILHO'!D3:D243,"KLORPAN 480 CE -1 LITRO",'CONFINAMENTO-MILHO'!F3:F243) -> 0 | J49: =COMPRAS!M49 -> 0.037619048 | K49: =I49*J49 -> 0 | M49: REEMBOLSO JEAN | N49: =N41+T41 -> 0
A50: 45690 | B50: 183 | H50: LANNATE | I50: =SUMIF('CONFINAMENTO-MILHO'!D3:D242,"LANNATE",'CONFINAMENTO-MILHO'!F3:F242) -> 800 | J50: =COMPRAS!M50 -> 0.05 | K50: =I50*J50 -> 40
A51: 45691 | B51: 180 | H51: MASTER 20-20-20 25 KG | I51: =SUMIF('CONFINAMENTO-MILHO'!D3:D243,"MASTER 20-20-20 25 KG",'CONFINAMENTO-MILHO'!F3:F243) -> 0 | J51: =COMPRAS!M51 -> 11.6 | K51: =I51*J51 -> 0
A52: 45692 | B52: 240 | H52: MAXIHUN 5 L | I52: =SUMIF('CONFINAMENTO-MILHO'!D3:D246,"MAXIHUN 5 L",'CONFINAMENTO-MILHO'!F3:F246) -> 0 | J52: =COMPRAS!M52 -> 0.023 | K52: =I52*J52 -> 0
A53: 45693 | B53: 180 | H53: MICROCOMPLEX 1X25 25K | I53: =SUMIF('CONFINAMENTO-MILHO'!D3:D226,"MICROCOMPLEX 1X25 25K",'CONFINAMENTO-MILHO'!F3:F226) -> 0 | J53: =COMPRAS!M53 -> 28 | K53: =I53*J53 -> 0
A54: 45694 | B54: 230 | H54: MINECTO PRO 12X1LT | I54: =SUMIF('CONFINAMENTO-MILHO'!D3:D243,"MINECTO PRO 12X1LT",'CONFINAMENTO-MILHO'!F3:F243) -> 0 | J54: =COMPRAS!M54 -> 0.23 | K54: =I54*J54 -> 0
A55: 45695 | B55: 360 | H55: MIRAVIS DUO 1 LITRO | I55: =SUMIF('CONFINAMENTO-MILHO'!D3:D227,"MIRAVIS DUO 1 LITRO",'CONFINAMENTO-MILHO'!F3:F227) -> 0 | J55: =COMPRAS!M55 -> 0.26 | K55: =I55*J55 -> 0
A56: 45696 | B56: 187 | H56: MULTICARE 1L | I56: =SUMIF('CONFINAMENTO-MILHO'!D3:D243,"MULTICARE 1L",'CONFINAMENTO-MILHO'!F3:F243) -> 0 | J56: =COMPRAS!M56 -> 0.052 | K56: =I56*J56 -> 0
A57: 45697 | B57: 290 | H57: N CALCIO CALCINIT YARA 15.5% 18CA 25K | I57: =SUMIF('CONFINAMENTO-MILHO'!D3:D222,"N CALCIO CALCINIT YARA 15.5% 18CA 25K",'CONFINAMENTO-MILHO'!F3:F222) -> 0 | J57: =COMPRAS!M57 -> 3.3718519 | K57: =I57*J57 -> 0
A58: 45698 | B58: 240 | H58: NITRATO DE POTASSIO 12% N 45% K2O 2%S 25 K | I58: =SUMIF('CONFINAMENTO-MILHO'!D3:D242,"NITRATO DE POTASSIO 12% N 45% K2O 2%S 25 K",'CONFINAMENTO-MILHO'!F3:F242) -> 0 | J58: =COMPRAS!M58 -> 8 | K58: =I58*J58 -> 0
A59: 45699 | B59: 240 | H59: NITRATO POTASSIO YARA TERA K 13-00-43 | I59: =SUMIF('CONFINAMENTO-MILHO'!D3:D235,"NITRATO POTASSIO YARA TERA K 13-00-43",'CONFINAMENTO-MILHO'!F3:F235) -> 40 | J59: =COMPRAS!M59 -> 8.5309091 | K59: =I59*J59 -> 341.23636
A60: 45700 | B60: 168 | H60: NITROCAM 12X1 LT | I60: =SUMIF('CONFINAMENTO-MILHO'!D3:D222,"NITROCAM 12X1 LT",'CONFINAMENTO-MILHO'!F3:F222) -> 0 | J60: =COMPRAS!M60 -> 0.048 | K60: =I60*J60 -> 0
A61: 45701 | B61: 240 | H61: NPK | I61: =SUMIF('CONFINAMENTO-MILHO'!D3:D222,"NPK ",'CONFINAMENTO-MILHO'!F3:F222) -> 104 | J61: =COMPRAS!M61 -> 4.2 | K61: =I61*J61 -> 436.8
A62: 45702 | B62: 211 | H62: NUPRID | I62: =SUMIF('CONFINAMENTO-MILHO'!D3:D222,"NUPRID",'CONFINAMENTO-MILHO'!F3:F222) -> 0 | J62: =COMPRAS!M62 -> 0
A63: 45703 | B63: 300 | H63: NUTRIGEMMA B ZN 5 LITROS | I63: =SUMIF('CONFINAMENTO-MILHO'!D3:D224,"NUTRIGEMMA B ZN 5 LITROS",'CONFINAMENTO-MILHO'!F3:F224) -> 0 | J63: =COMPRAS!M63 -> 0.068 | K63: =I63*J63 -> 0
A64: 45704 | B64: 250 | H64: NUTRISYSTEM INICIAL 42 06.30.06 25 K | I64: =SUMIF('CONFINAMENTO-MILHO'!D3:D224,"NUTRISYSTEM INICIAL 42 06.30.06 25 K",'CONFINAMENTO-MILHO'!F3:F224) -> 0 | J64: =COMPRAS!M64 -> 4.6
A65: 45705 | B65: 260 | H65: PADRON - 1 LITRO | I65: =SUMIF('CONFINAMENTO-MILHO'!D3:D224,"PADRON - 1 LITRO",'CONFINAMENTO-MILHO'!F3:F224) -> 0 | J65: =COMPRAS!M65 -> 0.09 | K65: =I65*J65 -> 0
A66: 45706 | B66: 360 | H66: PAGAMENTO FEITA DE MUDAS 2º PLANTIO | I66: =SUMIF('CONFINAMENTO-MILHO'!D3:D243,"PAGAMENTO FEITA DE MUDAS 2º PLANTIO",'CONFINAMENTO-MILHO'!F3:F243) -> 0 | J66: =COMPRAS!M66 -> 0.2 | K66: =I66*J66 -> 0
A67: 45707 | B67: 270 | H67: PHOSIFK CU4 1 LITRO | I67: =SUMIF('CONFINAMENTO-MILHO'!D3:D222,"PHOSIFK CU4 1 LITRO",'CONFINAMENTO-MILHO'!F3:F222) -> 0 | J67: =COMPRAS!M67 -> 0.098 | K67: =I67*J67 -> 0
A68: 45708 | B68: 240 | H68: PIRATE 1 LITRO | I68: =SUMIF('CONFINAMENTO-MILHO'!D3:D232,"PIRATE 1 LITRO",'CONFINAMENTO-MILHO'!F3:F232) -> 160 | J68: =COMPRAS!M68 -> 0.12166667 | K68: =I68*J68 -> 19.466667
A69: 45709 | B69: 250 | H69: PLATINUM NEO - GL 5 LITROS | I69: =SUMIF('CONFINAMENTO-MILHO'!D3:D234,"PLATINUM NEO - GL 5 LITROS",'CONFINAMENTO-MILHO'!F3:F234) -> 60 | J69: =COMPRAS!M69 -> 0.17333333 | K69: =I69*J69 -> 10.4
A70: 45710 | B70: 218 | H70: POQUER 4X5 LITROS | I70: =SUMIF('CONFINAMENTO-MILHO'!D3:D222,"POQUER 4X5 LITROS",'CONFINAMENTO-MILHO'!F3:F222) -> 0 | J70: =COMPRAS!M70 -> 0.0326 | K70: =I70*J70 -> 0
A71: 45711 | B71: 300 | H71: PRIMOLEO 1X20LT | I71: =SUMIF('CONFINAMENTO-MILHO'!D3:D222,"PRIMOLEO 1X20LT",'CONFINAMENTO-MILHO'!F3:F222) -> 0 | J71: =COMPRAS!M71 -> 0.023 | K71: =I71*J71 -> 0
A72: 45712 | B72: 360 | H72: PRIVILEGE 1L | I72: =SUMIF('CONFINAMENTO-MILHO'!D3:D228,"PRIVILEGE 1L",'CONFINAMENTO-MILHO'!F3:F228) -> 0 | J72: =COMPRAS!M72 -> 0.16 | K72: =I72*J72 -> 0
A73: 45713 | B73: 360 | H73: PROGIBB 400 - PCT 2,5 GR | I73: =SUMIF('CONFINAMENTO-MILHO'!D3:D228,"PROGIBB 400 - PCT 2,5 GR",'CONFINAMENTO-MILHO'!F3:F228) -> 0 | J73: =COMPRAS!M73 -> 6 | K73: =I73*J73 -> 0
A74: 45714 | B74: 345 | H74: PROTAMIN 25K | I74: =SUMIF('CONFINAMENTO-MILHO'!D3:D222,"PROTAMIN 25K",'CONFINAMENTO-MILHO'!F3:F222) -> 0 | J74: =COMPRAS!M74 -> 4.9 | K74: =I74*J74 -> 0
A75: 45715 | B75: 420 | H75: QUIMIFOL CALCIO E BORO II- BD 20 L | I75: =SUMIF('CONFINAMENTO-MILHO'!D3:D222,"QUIMIFOL CALCIO E BORO II- BD 20 L",'CONFINAMENTO-MILHO'!F3:F222) -> 0 | J75: =COMPRAS!M75 -> 0.0235 | K75: =I75*J75 -> 0
A76: 45716 | H76: QUIMIFOL IMPACTO - 1 LITRO | I76: =SUMIF('CONFINAMENTO-MILHO'!D3:D245,"IMPACTO 1L",'CONFINAMENTO-MILHO'!F3:F245) -> 0 | J76: =COMPRAS!M76 -> 0.22 | K76: =I76*J76 -> 0
A77: 45717 | B77: 246 | H77: QUIMIFOL P30W- GL 5 LITROS | I77: =SUMIF('CONFINAMENTO-MILHO'!D3:D228,"QUIMIFOL P30W- GL 5 LITROS",'CONFINAMENTO-MILHO'!F3:F228) -> 0 | J77: =COMPRAS!M77 -> 0.036 | K77: =I77*J77 -> 0
A78: 45718 | B78: 227 | H78: QUIMIFOL PERSIST- 1 LITRO | I78: =SUMIF('CONFINAMENTO-MILHO'!D3:D243,"QUIMIFOL PERSIST- 1 LITRO",'CONFINAMENTO-MILHO'!F3:F243) -> 0 | J78: =COMPRAS!M78 -> 0.036666667 | K78: =I78*J78 -> 0
A79: 45719 | B79: 360 | H79: QUIMIFOL PHFOS - 1 LITRO | I79: =SUMIF('CONFINAMENTO-MILHO'!D3:D228,"QUIMIFOL PHFOS - 1 LITRO",'CONFINAMENTO-MILHO'!F3:F228) -> 0 | J79: =COMPRAS!M79 -> 0.06 | K79: =I79*J79 -> 0
A80: 45720 | B80: 588 | H80: QUIMIFOL S450 - GL 5 LITROS | I80: =SUMIF('CONFINAMENTO-MILHO'!D3:D228,"QUIMIFOL S450 - GL 5 LITROS",'CONFINAMENTO-MILHO'!F3:F228) -> 360 | J80: =COMPRAS!M80 -> 0.042 | K80: =I80*J80 -> 15.12
A81: 45721 | B81: 120 | H81: QUIMIORGEN 20 N - GL DE 5 LITROS | I81: =SUMIF('CONFINAMENTO-MILHO'!D3:D243,"QUIMIORGEN 20 N - GL DE 5 LITROS",'CONFINAMENTO-MILHO'!F3:F243) -> 0 | J81: =COMPRAS!M81 -> 0.022 | K81: =I81*J81 -> 0
A82: 45722 | H82: RAPEL PCT- 3 KG | I82: =SUMIF('CONFINAMENTO-MILHO'!D3:D228,"RAPEL PCT- 3 KG",'CONFINAMENTO-MILHO'!F3:F228) -> 480 | J82: =COMPRAS!M82 -> 0.056666667 | K82: =I82*J82 -> 27.2
A83: 45723 | H83: RESTORER 5 LITROS | I83: =SUMIF('CONFINAMENTO-MILHO'!D3:D222,"RESTORER 5 LITROS",'CONFINAMENTO-MILHO'!F3:F222) -> 0 | J83: =COMPRAS!M83 -> 0.033111111 | K83: =I83*J83 -> 0
H84: RIDOMIL GOLD BRAVO 1 LITRO | I84: =SUMIF('CONFINAMENTO-MILHO'!D3:D222,"RIDOMIL GOLD BRAVO 1 LITRO",'CONFINAMENTO-MILHO'!F3:F222) -> 0 | J84: =COMPRAS!M84 -> 0.12 | K84: =I84*J84 -> 0
H85: RIDOMIL GOLD MZ 680 WG 12X1 1 KG | I85: =SUMIF('CONFINAMENTO-MILHO'!D3:D239,"RIDOMIL GOLD MZ 680 WG 12X1 1 KG",'CONFINAMENTO-MILHO'!F3:F239) -> 0 | J85: =COMPRAS!M85 -> 0.156 | K85: =I85*J85 -> 0
H86: RIZAMMINA 42 OS 8X2 5 KILOS | I86: =SUMIF('CONFINAMENTO-MILHO'!D3:D243,"RIZAMMINA 42 OS 8X2 5 KILOS",'CONFINAMENTO-MILHO'!F3:F243) -> 0 | J86: =COMPRAS!M86 -> 0.034 | K86: =I86*J86 -> 0
H87: ROUNDUP ORIGINAL MAIS - GL DE 5 L | I87: =SUMIF('CONFINAMENTO-MILHO'!D3:D243,"ROUNDUP ORIGINAL MAIS - GL DE 5 L",'CONFINAMENTO-MILHO'!F3:F243) -> 2300 | J87: =COMPRAS!M87 -> 0.03875 | K87: =I87*J87 -> 89.125
H88: SCORE 250 EC - 1 LITRO | I88: =SUMIF('CONFINAMENTO-MILHO'!D3:D228,"SCORE 250 EC - 1 LITRO",'CONFINAMENTO-MILHO'!F3:F228) -> 0 | J88: =COMPRAS!M88 -> 0.095 | K88: =I88*J88 -> 0
H89: SEMENTE DE MILHO BIOMATRIX 3066 | I89: =SUMIF('CONFINAMENTO-MILHO'!D3:D242,"SEMENTE DE MILHO BIOMATRIX 3066",'CONFINAMENTO-MILHO'!F3:F242) -> 8 | J89: =COMPRAS!M89 -> 67.5 | K89: =I89*J89 -> 540
H90: SEMENTE MELANCIA | I90: =SUMIF('CONFINAMENTO-MILHO'!D3:D240,"SEMENTE MELANCIA ",'CONFINAMENTO-MILHO'!F3:F240) -> 0 | J90: =COMPRAS!M90 -> 0
H91: SEMENTE MELANCIA CRIMSON SELE | I91: =SUMIF('CONFINAMENTO-MILHO'!D3:D228,"SEMENTE MELANCIA CRIMSON SELE",'CONFINAMENTO-MILHO'!F3:F228) -> 0 | J91: =COMPRAS!M91 -> 0.29 | K91: =I91*J91 -> 0
H92: SEMENTE MELANCIA H MANCHESTER | I92: =SUMIF('CONFINAMENTO-MILHO'!D3:D228,"SEMENTE MELANCIA H MANCHESTER",'CONFINAMENTO-MILHO'!F3:F228) -> 0 | J92: =COMPRAS!M92 -> 0.43 | K92: =I92*J92 -> 0
H93: SEMENTE MILHO HIB FEROZ SYN8A98 TL TG FORT VIP TURBO | I93: =SUMIF('CONFINAMENTO-MILHO'!D3:D228,"SEMENTE MILHO HIB FEROZ SYN8A98 TL TG FORT VIP TURBO",'CONFINAMENTO-MILHO'!F3:F228) -> 0 | J93: =COMPRAS!M93 -> 0.55 | K93: =I93*J93 -> 0
H94: SEMENTE MILHO HIB FEROZ SYN8A98 TL TG VIP FORTENZA | I94: =SUMIF('CONFINAMENTO-MILHO'!D3:D228,"SEMENTE MILHO HIB FEROZ SYN8A98 TL TG VIP FORTENZA",'CONFINAMENTO-MILHO'!F3:F228) -> 0 | J94: =COMPRAS!M94 -> 0.5 | K94: =I94*J94 -> 0
H95: SEMENTE TOMATE | I95: =SUMIF('CONFINAMENTO-MILHO'!D3:D223,"SEMENTE TOMATE ",'CONFINAMENTO-MILHO'!F3:F223) -> 0 | J95: =COMPRAS!M95 -> 0.54 | K95: =I95*J95 -> 0
H96: SEMENTE TOMATE COLT 1000 SEMENTES | I96: =SUMIF('CONFINAMENTO-MILHO'!D3:D228,"SEMENTE TOMATE COLT 1000 SEMENTES",'CONFINAMENTO-MILHO'!F3:F228) -> 0 | J96: =COMPRAS!M96 -> 0.57 | K96: =I96*J96 -> 0
H97: SENCOR 480 SC- 1 LITRO | I97: =SUMIF('CONFINAMENTO-MILHO'!D3:D228,"SENCOR 480 SC- 1 LITRO",'CONFINAMENTO-MILHO'!F3:F228) -> 0 | J97: =COMPRAS!M97 -> 0.14 | K97: =I97*J97 -> 0
H98: SPRAY DUNGER 20X1KG | I98: =SUMIF('CONFINAMENTO-MILHO'!D3:D222,"SPRAY DUNGER 20X1KG",'CONFINAMENTO-MILHO'!F3:F222) -> 0 | J98: =COMPRAS!M98 -> 0.08 | K98: =I98*J98 -> 0
H99: SPRINT ALGA TS 12X1LT | I99: =SUMIF('CONFINAMENTO-MILHO'!D3:D222,"SPRINT ALGA TS 12X1LT",'CONFINAMENTO-MILHO'!F3:F222) -> 0 | J99: =COMPRAS!M99 -> 0.2 | K99: =I99*J99 -> 0
H100: SUFATO DE AMONIO | I100: =SUMIF('CONFINAMENTO-MILHO'!D3:D222,"SUFATO DE AMONIO",'CONFINAMENTO-MILHO'!F3:F222) -> 40 | J100: =COMPRAS!M100 -> 2.4 | K100: =I100*J100 -> 96
...

Sheet TOMATE
A1: IRRIGAÇÃP SETOR 1 | D1: ADUBO | H1: APURAÇÃO | M1: MAQUINARIO-ADUBAÇÃO-PLANTIO--CAPINA | S1: VENENO
A2: DATA | B2: MINUTOS | D2: DESCRIÇÃO | E2: DATA | F2: QUANT | H2: DESCRIÇÃO | I2: TOTAL | J2: VALOR COMPRA | K2: CUSTO USADO | M2: DESCRIÇÃO | N2: DATA | O2: QUANT | P2: VALOR | Q2: TOTAL | S2: DESCRIÇÃO | T2: DATA | U2: QUANT | V2: VALOR | W2: TOTAL
D3: NUTRISYSTEM INICIAL 42 06.30.06 25 K | E3: 45630 | F3: 536.3 | H3: ABADIN 72 EC - 1 LITRO | I3: =SUMIF(TOMATE!D3:D243,"ABADIN 72 EC - 1 LITRO",TOMATE!F3:F243) -> 300 | J3: =COMPRAS!M3 -> 0.13 | K3: =I3*J3 -> 39 | M3: DIARIA RICARDO | N3: 45625 | O3: 0.5 | P3: 70 | Q3: =O3*P3 -> 35 | R3: R.FERNANDO | T3: 45636 | U3: 1.5 | V3: 10 | W3: =U3*V3 -> 15
D4: PRIMAZ | E4: 45630 | F4: 114.1 | H4: ABAMEX -1 LITRO | I4: =SUMIF(TOMATE!D3:D244,"ABAMEX -1 LITRO",TOMATE!F3:F244) -> 0 | J4: =COMPRAS!M4 -> 0.05 | K4: =I4*J4 -> 0 | M4: DIARIA AMIGO | N4: 45625 | O4: 0.5 | P4: 70 | Q4: =O4*P4 -> 35 | R4: R.FERNANDO | T4: 45643 | U4: 2 | V4: 10 | W4: =U4*V4 -> 20
D5: NUTRISYSTEM INICIAL 42 06.30.06 25 K | E5: 45630 | F5: -13.7 | H5: ABAMEX MAXX 72% 12X1 LT | I5: =SUMIF(TOMATE!D3:D244,"ABAMEX MAXX 72% 12X1 LT",TOMATE!F3:F244) -> 0 | J5: =COMPRAS!M5 -> 0.1 | K5: =I5*J5 -> 0 | M5: DIARIA RICARDO | N5: 45626 | O5: 0.5 | P5: 70 | Q5: =O5*P5 -> 35 | R5: R.FERNANDO | T5: 45646 | U5: 2 | V5: 10 | W5: =U5*V5 -> 20
D6: PRIMAZ | E6: 45630 | F6: -10.9 | H6: ACIDO BORICO SACO 25K | I6: =SUMIF(TOMATE!D3:D244,"ACIDO BORICO SACO 25K",TOMATE!F3:F244) -> 5.93 | J6: =COMPRAS!M6 -> 10.2 | K6: =I6*J6 -> 60.486 | M6: DIARIA AMIGO | N6: 45626 | O6: 0.5 | P6: 70 | Q6: =O6*P6 -> 35 | R6: R.FERNANDO | T6: 45652 | U6: 2 | V6: 10 | W6: =U6*V6 -> 20
D7: PLATINUM NEO - GL 5 LITROS | E7: 45636 | F7: 22.5 | H7: ADESIL - 1 LITRO | I7: =SUMIF(TOMATE!D3:D244,"ADESIL - 1 LITRO",TOMATE!F3:F244) -> 0 | J7: =COMPRAS!M7 -> 0.025 | K7: =I7*J7 -> 0 | M7: DIARIA MARKIN | N7: 45633 | O7: 1 | P7: 75 | Q7: =O7*P7 -> 75 | R7: R.FERNANDO | T7: 45657 | U7: 2 | V7: 10 | W7: =U7*V7 -> 20
D8: RIDOMIL GOLD BRAVO 1 LITRO | E8: 45636 | F8: 22.5 | H8: AGRUMAX MZ 4X5 KG | I8: =SUMIF(TOMATE!D3:D244,"AGRUMAX MZ 4X5 KG",TOMATE!F3:F244) -> 0 | J8: =COMPRAS!M8 -> 0.032 | K8: =I8*J8 -> 0 | M8: DIARIA MARKIN | N8: 45633 | O8: 1 | P8: 75 | Q8: =O8*P8 -> 75 | R8: R.FERNANDO | T8: 45660 | U8: 2 | V8: 10 | W8: =U8*V8 -> 20
D9: DRIPSOL INICIAL 15-30-15 25 KG | E9: 45637 | F9: 18.5 | H9: AMISTAR TOP 1 L | I9: =SUMIF(TOMATE!D3:D244,"AMISTAR TOP 1 L",TOMATE!F3:F244) -> 20 | J9: =COMPRAS!M9 -> 0.205 | K9: =I9*J9 -> 4.1 | M9: DIARIA MARKIN | N9: 45633 | O9: 0.5 | P9: 75 | Q9: =O9*P9 -> 37.5 | R9: R.FERNANDO | T9: 45663 | U9: 2 | V9: 10 | W9: =U9*V9 -> 20
D10: DRIPSOL INICIAL 15-30-15 25 KG | E10: 45642 | F10: 18.75 | H10: AMISTAR WG 6X500 G-1 KILO | I10: =SUMIF(TOMATE!D3:D244,"AMISTAR WG 6X500 G-1 KILO",TOMATE!F3:F244) -> 0 | J10: =COMPRAS!M10 -> 0.2 | K10: =I10*J10 -> 0 | M10: DIARIA MARKIN | N10: 45661 | O10: 2 | P10: 75 | Q10: =U8*P10 -> 150 | T10: 45666 | U10: 2 | V10: 10 | W10: =U10*V10 -> 20
D11: FULVUMIM 5 LITROS | E11: 45642 | F11: 1900 | H11: AMPLIGO 250 ML | I11: =SUMIF(TOMATE!D3:D244,"AMPLIGO 250 ML",TOMATE!F3:F244) -> 40 | J11: =COMPRAS!M11 -> 0.39 | K11: =I11*J11 -> 15.6 | M11: DIARIA LUCAS | N11: 45661 | O11: 3 | P11: 80 | Q11: =O11*P11 -> 240 | T11: 45671 | U11: 2 | V11: 10 | W11: =U11*V11 -> 20
D12: RESTORER 5 LITROS | E12: 45642 | F12: 190 | H12: AVATAR 1 L | I12: =SUMIF(TOMATE!D3:D244,"AVATAR 1 L",TOMATE!F3:F244) -> 240 | J12: =COMPRAS!M12 -> 0.375 | K12: =I12*J12 -> 90 | M12: DIDIU | N12: 45663 | O12: 1 | P12: 80 | Q12: =O12*P12 -> 80 | R12: R.JEAN | T12: 45674 | U12: 3 | V12: 10 | W12: =U12*V12 -> 30
D13: ACIDO BORICO SACO 25K | E13: 45642 | F13: 0.75 | H13: BARBANTE EM NOVELO N10 BRANCO | I13: =SUMIF(TOMATE!D3:D244,"BARBANTE EM NOVELO N10 BRANCO",TOMATE!F3:F244) -> 0 | J13: =COMPRAS!M13 -> 29.625 | K13: =I13*J13 -> 0 | M13: DIARIA MARKIN | N13: 45668 | O13: 2 | P13: 75 | Q13: =O13*P13 -> 150 | T13: 45676 | U13: 3 | V13: 10 | W13: =U13*V13 -> 30
D14: RIDOMIL GOLD MZ 680 WG 12X1 1 KG | E14: 45643 | F14: 100 | H14: BARBANTE EM NOVELO N8 OURO | I14: =SUMIF(TOMATE!D3:D244,"BARBANTE EM NOVELO N8 OURO",TOMATE!F3:F244) -> 0 | J14: =COMPRAS!M14 -> 31.576923 | K14: =I14*J14 -> 0 | M14: DIARIA LUCAS | N14: 45668 | O14: 1.5 | P14: 80 | Q14: =O14*P14 -> 120 | T14: 45680 | U14: 3 | V14: 10 | W14: =U14*V14 -> 30
D15: PRIVILEGE 1L | E15: 45643 | F15: 60 | H15: BENZOATO 1K | I15: =SUMIF(TOMATE!D3:D244,"BENZOATO 1K",TOMATE!F3:F244) -> 88 | J15: =COMPRAS!M15 -> 0.45 | K15: =I15*J15 -> 39.6 | M15: DIARIA LUCAS | N15: 45682 | O15: 5.5 | P15: 80 | Q15: =O15*P15 -> 440 | T15: 45681 | U15: 3 | V15: 10 | W15: =U15*V15 -> 30
D16: AMPLIGO 250 ML | E16: 45643 | F16: 40 | H16: BION 500 WG 25 G | I16: =SUMIF(TOMATE!D3:D244,"BION 500 WG 25 G",TOMATE!F3:F244) -> 2 | J16: =COMPRAS!M16 -> 2.8 | K16: =I16*J16 -> 5.6 | M16: DIARIA MARKIN | N16: 45682 | O16: 5 | P16: 75 | Q16: =O16*P16 -> 375 | T16: 45686 | U16: 3 | V16: 10 | W16: =U16*V16 -> 30
D17: FYLLOTON 12X1 1 LITRO | E17: 45646 | F17: 100 | H17: BRAVONIL ULTREX 1 KILO | I17: =SUMIF(TOMATE!D3:D244,"BRAVONIL ULTREX 1 KILO",TOMATE!F3:F244) -> 0 | J17: =COMPRAS!M17 -> 0.1 | K17: =I17*J17 -> 0 | M17: DIARIA LUCAS | N17: 45689 | O17: 4 | P17: 80 | Q17: =O17*P17 -> 320 | R17: R.FERNANDO | T17: 45693 | U17: 3 | V17: 10 | W17: =U17*V17 -> 30
D18: GLIBOR CA 5L | E18: 45646 | F18: 80 | H18: BRIT | I18: =SUMIF(TOMATE!D3:D244,"BRIT",TOMATE!F3:F244) -> 0 | J18: =COMPRAS!M18 -> 0.065 | K18: =I18*J18 -> 0 | M18: DIARIA MARKIN | N18: 45689 | O18: 2 | P18: 75 | Q18: =O18*P18 -> 150 | R18: R.FERNANDO | T18: 45697 | U18: 3 | V18: 10 | W18: =U18*V18 -> 30
D19: N CALCIO CALCINIT YARA 15.5% 18CA 25K | E19: 45650 | F19: 28 | H19: CAIXA PARA TOMATE | I19: =SUMIF(TOMATE!D3:D244,"CAIXA PARA TOMATE ",TOMATE!F3:F244) -> 0 | J19: =COMPRAS!M19 -> 0 | K19: =I19*J19 -> 0 | M19: DIARIA LUCAS | N19: 45696 | O19: 4.5 | P19: 80 | Q19: =O19*P19 -> 360 | R19: R.FERNANDO | T19: 45700 | U19: 3 | V19: 10 | W19: =U19*V19 -> 30
D20: FULVUMIM 5 LITROS | E20: 45650 | F20: 1850 | H20: CAL SUPER 5 LITROS | I20: =SUMIF(TOMATE!D3:D244,"CAL SUPER 5 LITROS",TOMATE!F3:F244) -> 0 | J20: =COMPRAS!M20 -> 0.044 | K20: =I20*J20 -> 0 | M20: FRETE GBI | N20: 45699 | O20: 1 | P20: 15 | Q20: =O20*P20 -> 15 | R20: R.FERNANDO | T20: 45703 | U20: 3 | V20: 10 | W20: =U20*V20 -> 30
D21: RESTORER 5 LITROS | E21: 45650 | F21: 1850 | H21: CARNADINE- 1 LITRO | I21: =SUMIF(TOMATE!D3:D244,"CARNADINE- 1 LITRO",TOMATE!F3:F244) -> 90 | J21: =COMPRAS!M21 -> 0.060833333 | K21: =I21*J21 -> 5.475 | M21: NRITATO DE CALCIO YARA | N21: 45701 | O21: 1 | P21: 85 | Q21: =O21*P21 -> 85 | R21: R.FERNANDO | T21: 45706 | U21: 3 | V21: 10 | W21: =U21*V21 -> 30
D22: DFULL 1 LITRO | E22: 45652 | F22: 80 | H22: CERCOBIN 875 WG- 1 KG | I22: =SUMIF(TOMATE!D3:D244,"CERCOBIN 875 WG- 1 KG",TOMATE!F3:F244) -> 0 | J22: =COMPRAS!M22 -> 0.085 | K22: =I22*J22 -> 0 | M22: DIARIA LUCAS | N22: 45705 | O22: 3 | P22: 80 | Q22: =O22*P22 -> 240 | R22: R.FERNANDO | T22: 45707 | U22: 3 | V22: 10 | W22: =U22*V22 -> 30
D23: D FIX - 1 LITRO | E23: 45652 | F23: 30 | H23: D FIX - 1 LITRO | I23: =SUMIF(TOMATE!D3:D244,"D FIX - 1 LITRO",TOMATE!F3:F244) -> 260 | J23: =COMPRAS!M23 -> 0.11 | K23: =I23*J23 -> 28.6 | M23: DIARIA LUCAS | N23: 45710 | O23: 4 | P23: 80 | Q23: =O23*P23 -> 320 | R23: R.FERNANDO | T23: 45708 | U23: 3 | V23: 10 | W23: =U23*V23 -> 30
D24: D S30 - 1 LITRO | E24: 45652 | F24: 30 | H24: D S30 - 1 LITRO | I24: =SUMIF(TOMATE!D3:D244,"D S30 - 1 LITRO",TOMATE!F3:F244) -> 260 | J24: =COMPRAS!M24 -> 0.065 | K24: =I24*J24 -> 16.9 | T24: 45711 | U24: 4 | V24: 10 | W24: =U24*V24 -> 40
D25: ABADIN 72 EC - 1 LITRO | E25: 45652 | F25: 60 | H25: DELEGATE(TM) - FR 120 GR | I25: =SUMIF(TOMATE!D3:D244,"DELEGATE(TM) - FR 120 GR",TOMATE!F3:F244) -> 20 | J25: =COMPRAS!M25 -> 2.75 | K25: =I25*J25 -> 55 | T25: 45715 | U25: 4 | V25: 10 | W25: =U25*V25 -> 40
D26: MINECTO PRO 12X1LT | E26: 45657 | F26: 40 | H26: DFULL 1 LITRO | I26: =SUMIF(TOMATE!D3:D244,"DFULL 1 LITRO",TOMATE!F3:F244) -> 665 | J26: =COMPRAS!M26 -> 0.155 | K26: =I26*J26 -> 103.075 | T26: 45717 | U26: 3 | V26: 10 | W26: =U26*V26 -> 30
D27: RIDOMIL GOLD MZ 680 WG 12X1 1 KG | E27: 45657 | F27: 60 | H27: DICARZOL 500 SP 12 X 500 GRS | I27: =SUMIF(TOMATE!D3:D244,"DICARZOL 500 SP 12 X 500 GRS",TOMATE!F3:F244) -> 0 | J27: =COMPRAS!M27 -> 0.76 | K27: =I27*J27 -> 0
D28: PIRATE 1 LITRO | E28: 45657 | F28: 60 | H28: DISPAROULTRA-S - GL DE 5 LITROS | I28: =SUMIF(TOMATE!D3:D244,"DISPAROULTRA-S - GL DE 5 LITROS",TOMATE!F3:F244) -> 0 | J28: =COMPRAS!M28 -> 0.028 | K28: =I28*J28 -> 0
D29: DRIPSOL MULTIPROPOSITO-18-18-18 25 K | E29: 45690 | F29: 37 | H29: DOMINUM XT-S - GL 5 LITROS | I29: =SUMIF(TOMATE!D3:D244,"DOMINUM XT-S - GL 5 LITROS",TOMATE!F3:F244) -> 0 | J29: =COMPRAS!M29 -> 0.128 | K29: =I29*J29 -> 0
D30: DFULL 1 LITRO | E30: 45660 | F30: 80 | H30: DRIPSOL BORO K 00.00.01+17% BORO 25 k | I30: =SUMIF(TOMATE!D3:D244,"DRIPSOL BORO K 00.00.01+17% BORO 25 k",TOMATE!F3:F244) -> 0 | J30: =COMPRAS!M30 -> 11.4 | K30: =I30*J30 -> 0
D31: D FIX - 1 LITRO | E31: 45660 | F31: 30 | H31: DRIPSOL CRESCIMENTO 24-10-10 25 KG | I31: =SUMIF(TOMATE!D3:D244,"DRIPSOL CRESCIMENTO 24-10-10 25 KG",TOMATE!F3:F244) -> 0 | J31: =COMPRAS!M31 -> 10.6 | K31: =I31*J31 -> 0
D32: D S30 - 1 LITRO | E32: 45660 | F32: 30 | H32: DRIPSOL INICIAL 15-30-15 25 KG | I32: =SUMIF(TOMATE!D3:D244,"DRIPSOL INICIAL 15-30-15 25 KG",TOMATE!F3:F244) -> 37.25 | J32: =COMPRAS!M32 -> 9.2769231 | K32: =I32*J32 -> 345.56538
D33: ABADIN 72 EC - 1 LITRO | E33: 45660 | F33: 60 | H33: DRIPSOL MICRO REXENE 700 GRAMAS | I33: =SUMIF(TOMATE!D3:D244,"DRIPSOL MICRO REXENE 700 GRAMAS",TOMATE!F3:F244) -> 0 | J33: =COMPRAS!M33 -> 0.082857143 | K33: =I33*J33 -> 0
D34: SULFATO DE MAGNESIO-KRISTA MGS 25K | E34: 45661 | F34: 15 | H34: DRIPSOL MULTIPROPOSITO-18-18-18 25 K | I34: =SUMIF(TOMATE!D3:D244,"DRIPSOL MULTIPROPOSITO-18-18-18 25 K",TOMATE!F3:F244) -> 79 | J34: =COMPRAS!M34 -> 10.56 | K34: =I34*J34 -> 834.24
D35: N CALCIO CALCINIT YARA 15.5% 18CA 25K | E35: 45663 | F35: 25 | H35: DRIPSOL PRODUÇÃO 12-06-40 25K | I35: =SUMIF(TOMATE!D3:D244,"DRIPSOL PRODUÇÃO 12-06-40 25K",TOMATE!F3:F244) -> 0 | J35: =COMPRAS!M35 -> 11 | K35: =I35*J35 -> 0 | N35: TOTAL | O35: =SUM(O3:O34) -> 44 | Q35: =SUM(Q3:Q34) -> 3372.5 | T35: TOTAL | U35: =SUM(U3:U31) -> 64.5 | W35: =SUM(W3:W31) -> 645
D36: FULVUMIM 5 LITROS | E36: 45663 | F36: 1900 | H36: ELEITTO | I36: =SUMIF(TOMATE!D3:D244,"ELEITTO",TOMATE!F3:F244) -> 0 | J36: =COMPRAS!M36 -> 0.33 | K36: =I36*J36 -> 0
D37: RESTORER 5 LITROS | E37: 45663 | F37: 1900 | H37: FERTIUM LIQUIDO 5L | I37: =SUMIF(TOMATE!D3:D244,"FERTIUM LIQUIDO 5L",TOMATE!F3:F244) -> 0 | J37: =COMPRAS!M37 -> 0.217 | K37: =I37*J37 -> 0
D38: MICROCOMPLEX 1X25 25K | E38: 45663 | F38: 0.95 | H38: FITILHO VIRGEM NOVELO NR 08 | I38: =SUMIF(TOMATE!D3:D244,"FITILHO VIRGEM NOVELO NR 08",TOMATE!F3:F244) -> 0 | J38: =COMPRAS!M38 -> 40 | K38: =I38*J38 -> 0 | M38: REEMBOLSO DE PAGAMENTO | S38: REEMBOLSO DE PAGAMENTO
D39: FULVUMIM 5 LITROS | E39: 45663 | F39: 100 | H39: FRETE CAIXAS TOMATE | I39: =SUMIF(TOMATE!D3:D244,"FRETE CAIXAS TOMATE ",TOMATE!F3:F244) -> 0 | J39: =COMPRAS!M39 -> 2.3571429 | K39: =I39*J39 -> 0 | M39: REEMBOLSO FERNANDO | N39: =SUMIF(TOMATE!R1:R30,"R.FERNANDO",TOMATE!Q1:Q30) -> 1817.5 | S39: REEMBOLSO FERNANDO | T39: =SUMIF(TOMATE!X1:X30,"R.FERNANDO",TOMATE!W1:W30) -> 0
D40: NUTRIGEMMA B ZN 5 LITROS | E40: 45663 | F40: 80 | H40: FTE 25K | I40: =SUMIF(TOMATE!D3:D244,"FTE 25K",TOMATE!F3:F244) -> 0 | J40: =COMPRAS!M40 -> 4.4 | K40: =I40*J40 -> 0 | M40: REEMBOLSO RAFAEL | N40: =SUMIF(TOMATE!R1:R30,"R.RAFAEL",TOMATE!Q1:Q30) -> 0 | S40: REEMBOLSO RAFAEL | T40: =SUMIF(TOMATE!X1:X30,"R.RAFAEL",TOMATE!W1:W30) -> 0
D41: SPRAY DUNGER 20X1KG | E41: 45663 | F41: 30 | H41: FULVUMIM 5 LITROS | I41: =SUMIF(TOMATE!D3:D244,"FULVUMIM 5 LITROS",TOMATE!F3:F244) -> 9400 | J41: =COMPRAS!M41 -> 0.025857143 | K41: =I41*J41 -> 243.05714 | M41: REEMBOLSO JEAN | N41: =SUMIF(TOMATE!R1:R30,"R.JEAN",TOMATE!Q1:Q30) -> 80 | S41: REEMBOLSO JEAN | T41: =SUMIF(TOMATE!X1:X30,"R.JEAN",TOMATE!W1:W30) -> 0
D42: MINECTO PRO 12X1LT | E42: 45666 | F42: 40 | H42: FYLLOTON 12X1 1 LITRO | I42: =SUMIF(TOMATE!D3:D244,"FYLLOTON 12X1 1 LITRO",TOMATE!F3:F244) -> 1280 | J42: =COMPRAS!M42 -> 0.067222222 | K42: =I42*J42 -> 86.044444
D43: AMISTAR TOP 1 L | E43: 45666 | F43: 20 | H43: GLIBOR CA 5L | I43: =SUMIF(TOMATE!D3:D244,"GLIBOR CA 5L",TOMATE!F3:F244) -> 590 | J43: =COMPRAS!M43 -> 0.046 | K43: =I43*J43 -> 27.14
D44: BION 500 WG 25 G | E44: 45666 | F44: 2 | H44: GLIMAN 30 4X5 KG | I44: =SUMIF(TOMATE!D3:D244,"GLIMAN 30 4X5 KG",TOMATE!F3:F244) -> 0 | J44: =COMPRAS!M44 -> 0.04 | K44: =I44*J44 -> 0
D45: PIRATE 1 LITRO | E45: 45671 | F45: 80 | H45: INTREPID240 SC -1 L | I45: =SUMIF(TOMATE!D3:D244,"INTREPID240 SC -1 L",TOMATE!F3:F244) -> 130 | J45: =COMPRAS!M45 -> 0.18 | K45: =I45*J45 -> 23.4
D46: DELEGATE(TM) - FR 120 GR | E46: 45671 | F46: 20 | H46: JOINER | I46: =SUMIF(TOMATE!D3:D244,"JOINER",TOMATE!F3:F244) -> 0 | J46: =COMPRAS!M46 -> 2.284 | K46: =I46*J46 -> 0 | M46: TOTAL REEMBOLSO
D47: RIDOMIL GOLD BRAVO 1 LITRO | E47: 45671 | F47: 80 | H47: K BOMBER 56 8X2 5 KILOS | I47: =SUMIF(TOMATE!D3:D244,"K BOMBER 56 8X2 5 KILOS ",TOMATE!F3:F244) -> 300 | J47: =COMPRAS!M47 -> 0.024 | K47: =I47*J47 -> 7.2 | M47: REEMBOLSO FERNANDO | N47: =N39+T39 -> 1817.5
D48: TIMOREX GOLD 12X1 LT | E48: 45674 | F48: 120 | H48: KIT COSTAL AZR PLUS - EPI | I48: =SUMIF(TOMATE!D3:D244,"KIT COSTAL AZR PLUS - EPI",TOMATE!F3:F244) -> 0 | J48: =COMPRAS!M48 -> 110 | K48: =I48*J48 -> 0 | M48: REEMBOLSO RAFAEL | N48: =N40+T40 -> 0
D49: MIRAVIS DUO 1 LITRO | E49: 45674 | F49: 60 | H49: KLORPAN 480 CE -1 LITRO | I49: =SUMIF(TOMATE!D3:D244,"KLORPAN 480 CE -1 LITRO",TOMATE!F3:F244) -> 0 | J49: =COMPRAS!M49 -> 0.037619048 | K49: =I49*J49 -> 0 | M49: REEMBOLSO JEAN | N49: =N41+T41 -> 80
D50: DRIPSOL MULTIPROPOSITO-18-18-18 25 K | E50: 45675 | F50: 38 | H50: LANNATE | I50: =SUMIF(TOMATE!D3:D244,"LANNATE",TOMATE!F3:F244) -> 0 | J50: =COMPRAS!M50 -> 0.05 | K50: =I50*J50 -> 0
D51: FULVUMIM 5 LITROS | E51: 45675 | F51: 1850 | H51: MASTER 20-20-20 25 KG | I51: =SUMIF(TOMATE!D3:D244,"MASTER 20-20-20 25 KG",TOMATE!F3:F244) -> 50 | J51: =COMPRAS!M51 -> 11.6 | K51: =I51*J51 -> 580
D52: RESTORER 5 LITROS | E52: 45675 | F52: 1850 | H52: MAXIHUN 5 L | I52: =SUMIF(TOMATE!D3:D244,"MAXIHUN 5 L",TOMATE!F3:F244) -> 0 | J52: =COMPRAS!M52 -> 0.023 | K52: =I52*J52 -> 0
D53: PIRATE 1 LITRO | E53: 45676 | F53: 120 | H53: MICROCOMPLEX 1X25 25K | I53: =SUMIF(TOMATE!D3:D244,"MICROCOMPLEX 1X25 25K",TOMATE!F3:F244) -> 2.11 | J53: =COMPRAS!M53 -> 28 | K53: =I53*J53 -> 59.08
D54: SPRAY DUNGER 20X1KG | E54: 45676 | F54: 90 | H54: MINECTO PRO 12X1LT | I54: =SUMIF(TOMATE!D3:D244,"MINECTO PRO 12X1LT",TOMATE!F3:F244) -> 155 | J54: =COMPRAS!M54 -> 0.23 | K54: =I54*J54 -> 35.65
D55: FYLLOTON 12X1 1 LITRO | E55: 45676 | F55: 150 | H55: MIRAVIS DUO 1 LITRO | I55: =SUMIF(TOMATE!D3:D244,"MIRAVIS DUO 1 LITRO",TOMATE!F3:F244) -> 60 | J55: =COMPRAS!M55 -> 0.26 | K55: =I55*J55 -> 15.6
D56: NUTRIGEMMA B ZN 5 LITROS | E56: 45680 | F56: 150 | H56: MULTICARE 1L | I56: =SUMIF(TOMATE!D3:D244,"MULTICARE 1L",TOMATE!F3:F244) -> 0 | J56: =COMPRAS!M56 -> 0.052 | K56: =I56*J56 -> 0
D57: GLIBOR CA 5L | E57: 45680 | F57: 150 | H57: N CALCIO CALCINIT YARA 15.5% 18CA 25K | I57: =SUMIF(TOMATE!D3:D244,"N CALCIO CALCINIT YARA 15.5% 18CA 25K",TOMATE!F3:F244) -> 179.5 | J57: =COMPRAS!M57 -> 3.3718519 | K57: =I57*J57 -> 605.24741
D58: FYLLOTON 12X1 1 LITRO | E58: 45680 | F58: 180 | H58: NITRATO DE POTASSIO 12% N 45% K2O 2%S 25 K | I58: =SUMIF(TOMATE!D3:D244,"NITRATO DE POTASSIO 12% N 45% K2O 2%S 25 K",TOMATE!F3:F244) -> 0 | J58: =COMPRAS!M58 -> 8 | K58: =I58*J58 -> 0
D59: AVATAR 1 L | E59: 45680 | F59: 120 | H59: NITRATO POTASSIO YARA TERA K 13-00-43 | I59: =SUMIF(TOMATE!D3:D244,"NITRATO POTASSIO YARA TERA K 13-00-43",TOMATE!F3:F244) -> 61 | J59: =COMPRAS!M59 -> 8.5309091 | K59: =I59*J59 -> 520.38545
D60: MINECTO PRO 12X1LT | E60: 45315 | F60: 75 | H60: NITROCAM 12X1 LT | I60: =SUMIF(TOMATE!D3:D244,"NITROCAM 12X1 LT",TOMATE!F3:F244) -> 150 | J60: =COMPRAS!M60 -> 0.048 | K60: =I60*J60 -> 7.2
D61: DFULL 1 LITRO | E61: 45315 | F61: 120 | H61: NPK | I61: =SUMIF(TOMATE!D3:D244,"NPK",TOMATE!F3:F244) -> 0 | J61: =COMPRAS!M61 -> 4.2 | K61: =I61*J61 -> 0
D62: D FIX - 1 LITRO | E62: 45315 | F62: 45 | H62: NUPRID | I62: =SUMIF(TOMATE!D3:D244,"NUPRID",TOMATE!F3:F244) -> 0 | J62: =COMPRAS!M62 -> 0
D63: D S30 - 1 LITRO | E63: 45315 | F63: 45 | H63: NUTRIGEMMA B ZN 5 LITROS | I63: =SUMIF(TOMATE!D3:D244,"NUTRIGEMMA B ZN 5 LITROS",TOMATE!F3:F244) -> 500 | J63: =COMPRAS!M63 -> 0.068 | K63: =I63*J63 -> 34
D64: N CALCIO CALCINIT YARA 15.5% 18CA 25K | E64: 45687 | F64: 38 | H64: NUTRISYSTEM INICIAL 42 06.30.06 25 K | I64: =SUMIF(TOMATE!D3:D244,"NUTRISYSTEM INICIAL 42 06.30.06 25 K",TOMATE!F3:F244) -> 522.6 | J64: =COMPRAS!M64 -> 4.6 | K64: =I64*J64 -> 2403.96
D65: FULVUMIM 5 LITROS | E65: 45687 | F65: 1800 | H65: PADRON - 1 LITRO | I65: =SUMIF(TOMATE!D3:D244,"PADRON - 1 LITRO",TOMATE!F3:F244) -> 0 | J65: =COMPRAS!M65 -> 0.09 | K65: =I65*J65 -> 0
D66: RESTORER 5 LITROS | E66: 45687 | F66: 1800 | H66: PAGAMENTO FEITA DE MUDAS 2º PLANTIO | I66: =SUMIF(TOMATE!D3:D244,"PAGAMENTO FEITA DE MUDAS 2º PLANTIO",TOMATE!F3:F244) -> 0 | J66: =COMPRAS!M66 -> 0.2 | K66: =I66*J66 -> 0
D67: DRIPSOL EQUILIBRIO | E67: 45687 | F67: 700 | H67: PHOSIFK CU4 1 LITRO | I67: =SUMIF(TOMATE!D3:D244,"PHOSIFK CU4 1 LITRO",TOMATE!F3:F244) -> 0 | J67: =COMPRAS!M67 -> 0.098 | K67: =I67*J67 -> 0
D68: MICROCOMPLEX 1X25 25K | E68: 45687 | F68: 1.16 | H68: PIRATE 1 LITRO | I68: =SUMIF(TOMATE!D3:D244,"PIRATE 1 LITRO",TOMATE!F3:F244) -> 470 | J68: =COMPRAS!M68 -> 0.12166667 | K68: =I68*J68 -> 57.183333
D69: AVATAR 1 L | E69: 45687 | F69: 120 | H69: PLATINUM NEO - GL 5 LITROS | I69: =SUMIF(TOMATE!D3:D244,"PLATINUM NEO - GL 5 LITROS",TOMATE!F3:F244) -> 112.5 | J69: =COMPRAS!M69 -> 0.17333333 | K69: =I69*J69 -> 19.5
D70: PRIVILEGE 1L | E70: 45687 | F70: 90 | H70: POQUER 4X5 LITROS | I70: =SUMIF(TOMATE!D3:D244,"POQUER 4X5 LITROS",TOMATE!F3:F244) -> 0 | J70: =COMPRAS!M70 -> 0.0326 | K70: =I70*J70 -> 0
D71: FYLLOTON 12X1 1 LITRO | E71: 45687 | F71: 150 | H71: PRIMOLEO 1X20LT | I71: =SUMIF(TOMATE!D3:D244,"PRIMOLEO 1X20LT",TOMATE!F3:F244) -> 0 | J71: =COMPRAS!M71 -> 0.023 | K71: =I71*J71 -> 0
D72: GLIBOR CA 5L | E72: 45687 | F72: 120 | H72: PRIVILEGE 1L | I72: =SUMIF(TOMATE!D3:D244,"PRIVILEGE 1L",TOMATE!F3:F244) -> 360 | J72: =COMPRAS!M72 -> 0.16 | K72: =I72*J72 -> 57.6
D73: FYLLOTON 12X1 1 LITRO | E73: 45693 | F73: 120 | H73: PROGIBB 400 - PCT 2,5 GR | I73: =SUMIF(TOMATE!D3:D244,"PROGIBB 400 - PCT 2,5 GR",TOMATE!F3:F244) -> 0 | J73: =COMPRAS!M73 -> 6 | K73: =I73*J73 -> 0
D74: SPRAY DUNGER 20X1KG | E74: 45693 | F74: 90 | H74: PROTAMIN 25K | I74: =SUMIF(TOMATE!D3:D244,"PROTAMIN 25K",TOMATE!F3:F244) -> 0 | J74: =COMPRAS!M74 -> 4.9 | K74: =I74*J74 -> 0
D75: NUTRIGEMMA B ZN 5 LITROS | E75: 45693 | F75: 90 | H75: QUIMIFOL CALCIO E BORO II- BD 20 L | I75: =SUMIF(TOMATE!D3:D244,"QUIMIFOL CALCIO E BORO II- BD 20 L",TOMATE!F3:F244) -> 0 | J75: =COMPRAS!M75 -> 0.0235 | K75: =I75*J75 -> 0
D76: N CALCIO CALCINIT YARA 15.5% 18CA 25K | E76: 45697 | F76: 54 | H76: QUIMIFOL IMPACTO - 1 LITRO | I76: =SUMIF(TOMATE!D3:D244,"QUIMIFOL IMPACTO - 1 LITRO",TOMATE!F3:F244) -> 0 | J76: =COMPRAS!M76 -> 0.22 | K76: =I76*J76 -> 0
D77: CLORETO DE POTASSIO | E77: 45697 | F77: 6.7 | H77: QUIMIFOL P30W- GL 5 LITROS | I77: =SUMIF(TOMATE!D3:D244,"QUIMIFOL P30W- GL 5 LITROS",TOMATE!F3:F244) -> 0 | J77: =COMPRAS!M77 -> 0.036 | K77: =I77*J77 -> 0
D78: NITRATO POTASSIO YARA TERA K 13-00-43 | E78: 45697 | F78: 11 | H78: QUIMIFOL PERSIST- 1 LITRO | I78: =SUMIF(TOMATE!D3:D244,"QUIMIFOL PERSIST- 1 LITRO",TOMATE!F3:F244) -> 0 | J78: =COMPRAS!M78 -> 0.036666667 | K78: =I78*J78 -> 0
D79: ACIDO BORICO SACO 25K | E79: 45697 | F79: 1.8 | H79: QUIMIFOL PHFOS - 1 LITRO | I79: =SUMIF(TOMATE!D3:D244,"QUIMIFOL PHFOS - 1 LITRO",TOMATE!F3:F244) -> 0 | J79: =COMPRAS!M79 -> 0.06 | K79: =I79*J79 -> 0
D80: FYLLOTON 12X1 1 LITRO | E80: 45697 | F80: 150 | H80: QUIMIFOL S450 - GL 5 LITROS | I80: =SUMIF(TOMATE!D3:D244,"QUIMIFOL S450 - GL 5 LITROS",TOMATE!F3:F244) -> 0 | J80: =COMPRAS!M80 -> 0.042 | K80: =I80*J80 -> 0
D81: SPRAY DUNGER 20X1KG | E81: 45697 | F81: 90 | H81: QUIMIORGEN 20 N - GL DE 5 LITROS | I81: =SUMIF(TOMATE!D3:D244,"QUIMIORGEN 20 N - GL DE 5 LITROS",TOMATE!F3:F244) -> 0 | J81: =COMPRAS!M81 -> 0.022 | K81: =I81*J81 -> 0
D82: PIRATE 1 LITRO | E82: 45697 | F82: 90 | H82: RAPEL PCT- 3 KG | I82: =SUMIF(TOMATE!D3:D244,"RAPEL PCT- 3 KG",TOMATE!F3:F244) -> 0 | J82: =COMPRAS!M82 -> 0.056666667 | K82: =I82*J82 -> 0
D83: PRIVILEGE 1L | E83: 45697 | F83: 120 | H83: RESTORER 5 LITROS | I83: =SUMIF(TOMATE!D3:D244,"RESTORER 5 LITROS",TOMATE!F3:F244) -> 7590 | J83: =COMPRAS!M83 -> 0.033111111 | K83: =I83*J83 -> 251.31333
D84: ABADIN 72 EC - 1 LITRO | E84: 45700 | F84: 90 | H84: RIDOMIL GOLD BRAVO 1 LITRO | I84: =SUMIF(TOMATE!D3:D244,"RIDOMIL GOLD BRAVO 1 LITRO",TOMATE!F3:F244) -> 102.5 | J84: =COMPRAS!M84 -> 0.12 | K84: =I84*J84 -> 12.3
D85: TRIGARD 750 PM - PCT 15 GR | E85: 45700 | F85: 9 | H85: RIDOMIL GOLD MZ 680 WG 12X1 1 KG | I85: =SUMIF(TOMATE!D3:D244,"RIDOMIL GOLD MZ 680 WG 12X1 1 KG",TOMATE!F3:F244) -> 160 | J85: =COMPRAS!M85 -> 0.156 | K85: =I85*J85 -> 24.96
D86: DFULL 1 LITRO | E86: 45700 | F86: 120 | H86: RIZAMMINA 42 OS 8X2 5 KILOS | I86: =SUMIF(TOMATE!D3:D244,"RIZAMMINA 42 OS 8X2 5 KILOS",TOMATE!F3:F244) -> 300 | J86: =COMPRAS!M86 -> 0.034 | K86: =I86*J86 -> 10.2
D87: D FIX - 1 LITRO | E87: 45700 | F87: 45 | H87: ROUNDUP ORIGINAL MAIS - GL DE 5 L | I87: =SUMIF(TOMATE!D3:D244,"ROUNDUP ORIGINAL MAIS - GL DE 5 L",TOMATE!F3:F244) -> 0 | J87: =COMPRAS!M87 -> 0.03875 | K87: =I87*J87 -> 0
D88: D S30 - 1 LITRO | E88: 45700 | F88: 45 | H88: SCORE 250 EC - 1 LITRO | I88: =SUMIF(TOMATE!D3:D244,"SCORE 250 EC - 1 LITRO",TOMATE!F3:F244) -> 0 | J88: =COMPRAS!M88 -> 0.095 | K88: =I88*J88 -> 0
D89: FYLLOTON 12X1 1 LITRO | E89: 45701 | F89: 150 | H89: SEMENTE DE MILHO BIOMATRIX 3066 | I89: =SUMIF(TOMATE!D3:D244,"SEMENTE DE MILHO BIOMATRIX 3066",TOMATE!F3:F244) -> 0 | J89: =COMPRAS!M89 -> 67.5 | K89: =I89*J89 -> 0
D90: NUTRIGEMMA B ZN 5 LITROS | E90: 45701 | F90: 90 | H90: SEMENTE MELANCIA | I90: =SUMIF(TOMATE!D3:D244,"SEMENTE MELANCIA",TOMATE!F3:F244) -> 0 | J90: =COMPRAS!M90 -> 0
D91: GLIBOR CA 5L | E91: 45701 | F91: 90 | H91: SEMENTE MELANCIA CRIMSON SELE | I91: =SUMIF(TOMATE!D3:D244,"SEMENTE MELANCIA CRIMSON SELE",TOMATE!F3:F244) -> 0 | J91: =COMPRAS!M91 -> 0.29 | K91: =I91*J91 -> 0
D92: SPRAY DUNGER 20X1KG | E92: 45701 | F92: 90 | H92: SEMENTE MELANCIA H MANCHESTER | I92: =SUMIF(TOMATE!D3:D244,"SEMENTE MELANCIA H MANCHESTER",TOMATE!F3:F244) -> 0 | J92: =COMPRAS!M92 -> 0.43 | K92: =I92*J92 -> 0
D93: N CALCIO CALCINIT YARA 15.5% 18CA 25K | E93: 45702 | F93: 25 | H93: SEMENTE MILHO HIB FEROZ SYN8A98 TL TG FORT VIP TURBO | I93: =SUMIF(TOMATE!D3:D244,"SEMENTE MILHO HIB FEROZ SYN8A98 TL TG FORT VIP TURBO",TOMATE!F3:F244) -> 0 | J93: =COMPRAS!M93 -> 0.55 | K93: =I93*J93 -> 0
D94: NITRATO POTASSIO YARA TERA K 13-00-43 | E94: 45702 | F94: 25 | H94: SEMENTE MILHO HIB FEROZ SYN8A98 TL TG VIP FORTENZA | I94: =SUMIF(TOMATE!D3:D244,"SEMENTE MILHO HIB FEROZ SYN8A98 TL TG VIP FORTENZA",TOMATE!F3:F244) -> 0 | J94: =COMPRAS!M94 -> 0.5 | K94: =I94*J94 -> 0
D95: ACIDO BORICO SACO 25K | E95: 45702 | F95: 1.58 | H95: SEMENTE TOMATE | I95: =SUMIF(TOMATE!D3:D244,"SEMENTE TOMATE ",TOMATE!F3:F244) -> 0 | J95: =COMPRAS!M95 -> 0.54 | K95: =I95*J95 -> 0
D96: PIRATE 1 LITRO | E96: 45703 | F96: 120 | H96: SEMENTE TOMATE COLT 1000 SEMENTES | I96: =SUMIF(TOMATE!D3:D244,"SEMENTE TOMATE COLT 1000 SEMENTES",TOMATE!F3:F244) -> 0 | J96: =COMPRAS!M96 -> 0.57 | K96: =I96*J96 -> 0
D97: PRIVILEGE 1L | E97: 45703 | F97: 90 | H97: SENCOR 480 SC- 1 LITRO | I97: =SUMIF(TOMATE!D3:D244,"SENCOR 480 SC- 1 LITRO",TOMATE!F3:F244) -> 240 | J97: =COMPRAS!M97 -> 0.14 | K97: =I97*J97 -> 33.6
D98: NITROCAM 12X1 LT | E98: 45703 | F98: 150 | H98: SPRAY DUNGER 20X1KG | I98: =SUMIF(TOMATE!D3:D244,"SPRAY DUNGER 20X1KG",TOMATE!F3:F244) -> 480 | J98: =COMPRAS!M98 -> 0.08 | K98: =I98*J98 -> 38.4
D99: CARNADINE- 1 LITRO | E99: 45703 | F99: 90 | H99: SPRINT ALGA TS 12X1LT | I99: =SUMIF(TOMATE!D3:D244,"SPRINT ALGA TS 12X1LT",TOMATE!F3:F244) -> 21 | J99: =COMPRAS!M99 -> 0.2 | K99: =I99*J99 -> 4.2
D100: DRIPSOL MULTIPROPOSITO-18-18-18 25 K | E100: 45706 | F100: 4 | H100: SUFATO DE AMONIO | I100: =SUMIF(TOMATE!D3:D244,"SUFATO DE AMONIO",TOMATE!F3:F244) -> 0 | J100: =COMPRAS!M100 -> 2.4 | K100: =I100*J100 -> 0
...

Sheet COMPRAS
A1: COMPRAS CONFINAMENTO | J1: EQUIPARAÇÃO DE PREÇOS
A2: DESCRIÇÃO | B2: DATA | C2: QUANT | D2: UNIDADE | E2: TOTAL | F2: VALOR | G2: FORNECEDOR/N DE NOTA | H2: COMPRADO POR | J2: DESCRIÇÃO | K2: COMPRA TOTAL | L2: VALOR TOTAL | M2: PREÇO EQUIPARADO
A3: ADESIL - 1 LITRO | B3: 45299 | C3: 1 | D3: 1000 | E3: =C3*D3 -> 1000 | F3: 25 | G3: UNIAGRO NOTA 58496 | J3: ABADIN 72 EC - 1 LITRO | K3: =SUMIF(COMPRAS!A3:A183,"ABADIN 72 EC - 1 LITRO",COMPRAS!E3:E183) -> 2000 | L3: =SUMIF(COMPRAS!A3:A183,"ABADIN 72 EC - 1 LITRO",COMPRAS!F3:F183) -> 260 | M3: =L3/K3 -> 0.13
A4: PLATINUM NEO - GL 5 LITROS | B4: 45299 | C4: 1 | D4: 5000 | E4: =C4*D4 -> 5000 | F4: 1000 | G4: UNIAGRO NOTA 58496 | J4: ABAMEX -1 LITRO | K4: =SUMIF(COMPRAS!A3:A183,"ABAMEX -1 LITRO",COMPRAS!E3:E183) -> 1000 | L4: =SUMIF(COMPRAS!A3:A183,"ABAMEX -1 LITRO",COMPRAS!F3:F183) -> 50 | M4: =L4/K4 -> 0.05
A5: QUIMIFOL P30W- GL 5 LITROS | B5: 45299 | C5: 1 | D5: 5000 | E5: =C5*D5 -> 5000 | F5: 180 | G5: UNIAGRO NOTA 58496 | J5: ABAMEX MAXX 72% 12X1 LT | K5: =SUMIF(COMPRAS!A3:A183,"ABAMEX MAXX 72% 12X1 LT",COMPRAS!E3:E183) -> 1000 | L5: =SUMIF(COMPRAS!A3:A183,"ABAMEX MAXX 72% 12X1 LT",COMPRAS!F3:F183) -> 100 | M5: =L5/K5 -> 0.1
A6: QUIMIFOL PHFOS - 1 LITRO | B6: 45299 | C6: 1 | D6: 1000 | E6: =C6*D6 -> 1000 | F6: 60 | G6: UNIAGRO NOTA 58496 | J6: ACIDO BORICO SACO 25K | K6: =SUMIF(COMPRAS!A3:A183,"ACIDO BORICO SACO 25K",COMPRAS!E3:E183) -> 25 | L6: =SUMIF(COMPRAS!A3:A183,"ACIDO BORICO SACO 25K",COMPRAS!F3:F183) -> 255 | M6: =L6/K6 -> 10.2
A7: ROUNDUP ORIGINAL MAIS - GL DE 5 L | B7: 45299 | C7: 1 | D7: 5000 | E7: =C7*D7 -> 5000 | F7: 195 | G7: UNIAGRO NOTA 58496 | J7: ADESIL - 1 LITRO | K7: =SUMIF(COMPRAS!A3:A183,"ADESIL - 1 LITRO",COMPRAS!E3:E183) -> 1000 | L7: =SUMIF(COMPRAS!A3:A183,"ADESIL - 1 LITRO",COMPRAS!F3:F183) -> 25 | M7: =L7/K7 -> 0.025
A8: ABADIN 72 EC - 1 LITRO | B8: 45309 | C8: 2 | D8: 1000 | E8: =C8*D8 -> 2000 | F8: 260 | G8: UNIAGRO NOTA 59051 | J8: AGRUMAX MZ 4X5 KG | K8: =SUMIF(COMPRAS!A3:A183,"AGRUMAX MZ 4X5 KG",COMPRAS!E3:E183) -> 5000 | L8: =SUMIF(COMPRAS!A3:A183,"AGRUMAX MZ 4X5 KG",COMPRAS!F3:F183) -> 160 | M8: =L8/K8 -> 0.032
A9: ABAMEX -1 LITRO | B9: 45309 | C9: 1 | D9: 1000 | E9: =C9*D9 -> 1000 | F9: 50 | G9: UNIAGRO NOTA 59051 | J9: AMISTAR TOP 1 L | K9: =SUMIF(COMPRAS!A3:A183,"AMISTAR TOP 1 L",COMPRAS!E3:E183) -> 1000 | L9: =SUMIF(COMPRAS!A3:A183,"AMISTAR TOP 1 L",COMPRAS!F3:F183) -> 205 | M9: =L9/K9 -> 0.205
A10: KLORPAN 480 CE -1 LITRO | B10: 45309 | C10: 10 | D10: 1000 | E10: =C10*D10 -> 10000 | F10: 380 | G10: UNIAGRO NOTA 59051 | J10: AMISTAR WG 6X500 G-1 KILO | K10: =SUMIF(COMPRAS!A3:A183,"AMISTAR WG 6X500 G-1 KILO",COMPRAS!E3:E183) -> 1000 | L10: =SUMIF(COMPRAS!A3:A183,"AMISTAR WG 6X500 G-1 KILO",COMPRAS!F3:F183) -> 200 | M10: =L10/K10 -> 0.2
A11: QUIMIFOL IMPACTO - 1 LITRO | B11: 45309 | C11: 1 | D11: 1000 | E11: =C11*D11 -> 1000 | F11: 220 | G11: UNIAGRO NOTA 59051 | J11: AMPLIGO 250 ML | K11: =SUMIF(COMPRAS!A3:A183,"AMPLIGO 250 ML",COMPRAS!E3:E183) -> 1000 | L11: =SUMIF(COMPRAS!A3:A183,"AMPLIGO 250 ML",COMPRAS!F3:F183) -> 390 | M11: =L11/K11 -> 0.39
A12: SEMENTE MELANCIA CRIMSON SELE | B12: 45309 | C12: 1 | D12: 1000 | E12: =C12*D12 -> 1000 | F12: 290 | G12: UNIAGRO NOTA 59051 | J12: AVATAR 1 L | K12: =SUMIF(COMPRAS!A3:A183,"AVATAR 1 L",COMPRAS!E3:E183) -> 2000 | L12: =SUMIF(COMPRAS!A3:A183,"AVATAR 1 L",COMPRAS!F3:F183) -> 750 | M12: =L12/K12 -> 0.375
A13: DICARZOL 500 SP 12 X 500 GRS | B13: 45321 | C13: 1 | D13: 500 | E13: =C13*D13 -> 500 | F13: 380 | G13: UNIAGRO NOTA 59471 | J13: BARBANTE EM NOVELO N10 BRANCO | K13: =SUMIF(COMPRAS!A3:A183,"BARBANTE EM NOVELO N10 BRANCO",COMPRAS!E3:E183) -> 40 | L13: =SUMIF(COMPRAS!A3:A183,"BARBANTE EM NOVELO N10 BRANCO",COMPRAS!F3:F183) -> 1185 | M13: =L13/K13 -> 29.625
A14: QUIMIFOL S450 - GL 5 LITROS | B14: 45321 | C14: 1 | D14: 5000 | E14: =C14*D14 -> 5000 | F14: 210 | G14: UNIAGRO NOTA 59471 | J14: BARBANTE EM NOVELO N8 OURO | K14: =SUMIF(COMPRAS!A3:A183,"BARBANTE EM NOVELO N8 OURO",COMPRAS!E3:E183) -> 26 | L14: =SUMIF(COMPRAS!A3:A183,"BARBANTE EM NOVELO N8 OURO",COMPRAS!F3:F183) -> 821 | M14: =L14/K14 -> 31.576923
A15: RAPEL PCT- 3 KG | B15: 45321 | C15: 1 | D15: 3000 | E15: =C15*D15 -> 3000 | F15: 170 | G15: UNIAGRO NOTA 59471 | J15: BENZOATO 1K | K15: =SUMIF(COMPRAS!A3:A183,"BENZOATO 1K",COMPRAS!E3:E183) -> 1000 | L15: =SUMIF(COMPRAS!A3:A183,"BENZOATO 1K",COMPRAS!F3:F183) -> 450 | M15: =L15/K15 -> 0.45
A16: ROUNDUP ORIGINAL MAIS - GL DE 5 L | B16: 45321 | C16: 1 | D16: 5000 | E16: =C16*D16 -> 5000 | F16: 220 | G16: UNIAGRO NOTA 59471 | J16: BION 500 WG 25 G | K16: =SUMIF(COMPRAS!A3:A183,"BION 500 WG 25 G",COMPRAS!E3:E183) -> 75 | L16: =SUMIF(COMPRAS!A3:A183,"BION 500 WG 25 G",COMPRAS!F3:F183) -> 210 | M16: =L16/K16 -> 2.8
A17: KLORPAN 480 CE -1 LITRO | B17: 45328 | C17: 1 | D17: 1000 | E17: =C17*D17 -> 1000 | F17: 50 | G17: UNIAGRO NOTA 59729 | J17: BRAVONIL ULTREX 1 KILO | K17: =SUMIF(COMPRAS!A3:A183,"BRAVONIL ULTREX 1 KILO",COMPRAS!E3:E183) -> 1000 | L17: =SUMIF(COMPRAS!A3:A183,"BRAVONIL ULTREX 1 KILO",COMPRAS!F3:F183) -> 100 | M17: =L17/K17 -> 0.1
A18: RAPEL PCT- 3 KG | B18: 45328 | C18: 1 | D18: 3000 | E18: =C18*D18 -> 3000 | F18: 170 | G18: UNIAGRO NOTA 59729 | J18: BRIT | K18: =SUMIF(COMPRAS!A3:A183,"BRIT ",COMPRAS!E3:E183) -> 1000 | L18: =SUMIF(COMPRAS!A3:A183,"BRIT ",COMPRAS!F3:F183) -> 65 | M18: =L18/K18 -> 0.065
A19: CARNADINE- 1 LITRO | B19: 45329 | C19: 1 | D19: 1000 | E19: =C19*D19 -> 1000 | F19: 65 | G19: UNIAGRO NOTA 59811 | J19: CAIXA PARA TOMATE
A20: CERCOBIN 875 WG- 1 KG | B20: 45329 | C20: 1 | D20: 1000 | E20: =C20*D20 -> 1000 | F20: 85 | G20: UNIAGRO NOTA 59811 | J20: CAL SUPER 5 LITROS | K20: =SUMIF(COMPRAS!A3:A183,"CAL SUPER 5 LITROS",COMPRAS!E3:E183) -> 5000 | L20: =SUMIF(COMPRAS!A3:A183,"CAL SUPER 5 LITROS",COMPRAS!F3:F183) -> 220 | M20: =L20/K20 -> 0.044
A21: QUIMIFOL CALCIO E BORO II- BD 20 L | B21: 45329 | C21: 1 | D21: 20000 | E21: =C21*D21 -> 20000 | F21: 470 | G21: UNIAGRO NOTA 59811 | J21: CARNADINE- 1 LITRO | K21: =SUMIF(COMPRAS!A3:A183,"CARNADINE- 1 LITRO",COMPRAS!E3:E183) -> 6000 | L21: =SUMIF(COMPRAS!A3:A183,"CARNADINE- 1 LITRO",COMPRAS!F3:F183) -> 365 | M21: =L21/K21 -> 0.060833333
A22: SCORE 250 EC - 1 LITRO | B22: 45329 | C22: 1 | D22: 1000 | E22: =C22*D22 -> 1000 | F22: 95 | G22: UNIAGRO NOTA 59811 | J22: CERCOBIN 875 WG- 1 KG | K22: =SUMIF(COMPRAS!A3:A183,"CERCOBIN 875 WG- 1 KG",COMPRAS!E3:E183) -> 1000 | L22: =SUMIF(COMPRAS!A3:A183,"CERCOBIN 875 WG- 1 KG",COMPRAS!F3:F183) -> 85 | M22: =L22/K22 -> 0.085
A23: CARNADINE- 1 LITRO | B23: 45341 | C23: 1 | D23: 5000 | E23: =C23*D23 -> 5000 | F23: 300 | G23: UNIAGRO NOTA 60135 | J23: D FIX - 1 LITRO | K23: =SUMIF(COMPRAS!A3:A183,"D FIX - 1 LITRO",COMPRAS!E3:E183) -> 1000 | L23: =SUMIF(COMPRAS!A3:A183,"D FIX - 1 LITRO",COMPRAS!F3:F183) -> 110 | M23: =L23/K23 -> 0.11
A24: PROGIBB 400 - PCT 2,5 GR | B24: 45440 | C24: 16 | D24: 2.5 | E24: =C24*D24 -> 40 | F24: 240 | G24: UNIAGRO NOTA 61385 | J24: D S30 - 1 LITRO | K24: =SUMIF(COMPRAS!A3:A183,"D S30 - 1 LITRO",COMPRAS!E3:E183) -> 1000 | L24: =SUMIF(COMPRAS!A3:A183,"D S30 - 1 LITRO",COMPRAS!F3:F183) -> 65 | M24: =L24/K24 -> 0.065
A25: AMISTAR WG 6X500 G-1 KILO | B25: 45498 | C25: 1 | D25: 1000 | E25: =C25*D25 -> 1000 | F25: 200 | G25: TABELA ANTIGA DO TOMATE COMPRAS RAMON | J25: DELEGATE(TM) - FR 120 GR | K25: =SUMIF(COMPRAS!A3:A183,"DELEGATE(TM) - FR 120 GR",COMPRAS!E3:E183) -> 480 | L25: =SUMIF(COMPRAS!A3:A183,"DELEGATE(TM) - FR 120 GR",COMPRAS!F3:F183) -> 1320 | M25: =L25/K25 -> 2.75
A26: TOPMIX 03-28-00 YARA 50K | B26: 45509 | C26: 13 | D26: 25 | E26: =C26*D26 -> 325 | F26: 2210 | G26: HF NOTA 43526 | H26: CONFINAMENTO/FERNANDO | J26: DFULL 1 LITRO | K26: =SUMIF(COMPRAS!A3:A183,"DFULL 1 LITRO",COMPRAS!E3:E183) -> 2000 | L26: =SUMIF(COMPRAS!A3:A183,"DFULL 1 LITRO",COMPRAS!F3:F183) -> 310 | M26: =L26/K26 -> 0.155
A27: QUIMIFOL TQ CLEAR - 1 LITRO | B27: 45512 | C27: 1 | D27: 1000 | E27: =C27*D27 -> 1000 | F27: 95 | G27: UNIAGRO NOTA 61956 | J27: DICARZOL 500 SP 12 X 500 GRS | K27: =SUMIF(COMPRAS!A3:A183,"DICARZOL 500 SP 12 X 500 GRS",COMPRAS!E3:E183) -> 500 | L27: =SUMIF(COMPRAS!A3:A183,"DICARZOL 500 SP 12 X 500 GRS",COMPRAS!F3:F183) -> 380 | M27: =L27/K27 -> 0.76
A28: DRIPSOL INICIAL 15-30-15 25 KG | B28: 45520 | C28: 10 | D28: 25 | E28: =C28*D28 -> 250 | F28: 2260 | G28: HF NOTA 43697 | H28: CONFINAMENTO/RAFAEL | J28: DISPAROULTRA-S - GL DE 5 LITROS | K28: =SUMIF(COMPRAS!A3:A183,"DISPAROULTRA-S - GL DE 5 LITROS",COMPRAS!E3:E183) -> 5000 | L28: =SUMIF(COMPRAS!A3:A183,"DISPAROULTRA-S - GL DE 5 LITROS",COMPRAS!F3:F183) -> 140 | M28: =L28/K28 -> 0.028
A29: FULVUMIM 5 LITROS | B29: 45520 | C29: 4 | D29: 5000 | E29: =C29*D29 -> 20000 | F29: 660 | G29: HF NOTA 43697 | H29: CONFINAMENTO/RAFAEL | J29: DOMINUM XT-S - GL 5 LITROS | K29: =SUMIF(COMPRAS!A3:A183,"DOMINUM XT-S - GL 5 LITROS",COMPRAS!E3:E183) -> 10000 | L29: =SUMIF(COMPRAS!A3:A183,"DOMINUM XT-S - GL 5 LITROS",COMPRAS!F3:F183) -> 1280 | M29: =L29/K29 -> 0.128
A30: RESTORER 5 LITROS | B30: 45520 | C30: 3 | D30: 5000 | E30: =C30*D30 -> 15000 | F30: 480 | G30: HF NOTA 43697 | H30: CONFINAMENTO/RAFAEL | J30: DRIPSOL BORO K 00.00.01+17% BORO 25 k | K30: =SUMIF(COMPRAS!A3:A183,"DRIPSOL BORO K 00.00.01+17% BORO 25 k",COMPRAS!E3:E183) -> 25 | L30: =SUMIF(COMPRAS!A3:A183,"DRIPSOL BORO K 00.00.01+17% BORO 25 k",COMPRAS!F3:F183) -> 285 | M30: =L30/K30 -> 11.4
A31: BION 500 WG 25 G | B31: 45524 | C31: 3 | D31: 25 | E31: =C31*D31 -> 75 | F31: 210 | G31: HF NOTA 43754 | H31: CONFINAMENTO/RAFAEL | J31: DRIPSOL CRESCIMENTO 24-10-10 25 KG | K31: =SUMIF(COMPRAS!A3:A183,"DRIPSOL CRESCIMENTO 24-10-10 25 KG",COMPRAS!E3:E183) -> 25 | L31: =SUMIF(COMPRAS!A3:A183,"DRIPSOL CRESCIMENTO 24-10-10 25 KG",COMPRAS!F3:F183) -> 265 | M31: =L31/K31 -> 10.6
A32: DRIPSOL MICRO REXENE 700 GRAMAS | B32: 45524 | C32: 2 | D32: 700 | E32: =C32*D32 -> 1400 | F32: 116 | G32: HF NOTA 43754 | H32: CONFINAMENTO/RAFAEL | J32: DRIPSOL INICIAL 15-30-15 25 KG | K32: =SUMIF(COMPRAS!A3:A183,"DRIPSOL INICIAL 15-30-15 25 KG",COMPRAS!E3:E183) -> 325 | L32: =SUMIF(COMPRAS!A3:A183,"DRIPSOL INICIAL 15-30-15 25 KG",COMPRAS!F3:F183) -> 3015 | M32: =L32/K32 -> 9.2769231
A33: DRIPSOL MULTIPROPOSITO-18-18-18 25 K | B33: 45524 | C33: 5 | D33: 25 | E33: =C33*D33 -> 125 | F33: 1325 | G33: HF NOTA 43754 | H33: CONFINAMENTO/RAFAEL | J33: DRIPSOL MICRO REXENE 700 GRAMAS | K33: =SUMIF(COMPRAS!A3:A183,"DRIPSOL MICRO REXENE 700 GRAMAS",COMPRAS!E3:E183) -> 1400 | L33: =SUMIF(COMPRAS!A3:A183,"DRIPSOL MICRO REXENE 700 GRAMAS",COMPRAS!F3:F183) -> 116 | M33: =L33/K33 -> 0.082857143
A34: FYLLOTON 12X1 1 LITRO | B34: 45524 | C34: 3 | D34: 1000 | E34: =C34*D34 -> 3000 | F34: 210 | G34: HF NOTA 43754 | H34: CONFINAMENTO/RAFAEL | J34: DRIPSOL MULTIPROPOSITO-18-18-18 25 K | K34: =SUMIF(COMPRAS!A3:A183,"DRIPSOL MULTIPROPOSITO-18-18-18 25 K",COMPRAS!E3:E183) -> 550 | L34: =SUMIF(COMPRAS!A3:A183,"DRIPSOL MULTIPROPOSITO-18-18-18 25 K",COMPRAS!F3:F183) -> 5808 | M34: =L34/K34 -> 10.56
A35: N CALCIO CALCINIT YARA 15.5% 18CA 25K | B35: 45524 | C35: 3 | D35: 25 | E35: =C35*D35 -> 75 | F35: 270 | G35: HF NOTA 43754 | H35: CONFINAMENTO/RAFAEL | J35: DRIPSOL PRODUÇÃO 12-06-40 25K | K35: =SUMIF(COMPRAS!A3:A183,"DRIPSOL PRODUÇÃO 12-06-40 25K",COMPRAS!E3:E183) -> 25 | L35: =SUMIF(COMPRAS!A3:A183,"DRIPSOL PRODUÇÃO 12-06-40 25K",COMPRAS!F3:F183) -> 275 | M35: =L35/K35 -> 11
A36: POQUER 4X5 LITROS | B36: 45524 | C36: 1 | D36: 5000 | E36: =C36*D36 -> 5000 | F36: 163 | G36: HF NOTA 43754 | H36: CONFINAMENTO/RAFAEL | J36: ELEITTO | K36: =SUMIF(COMPRAS!A3:A183,"ELEITTO",COMPRAS!E3:E183) -> 1000 | L36: =SUMIF(COMPRAS!A3:A183,"ELEITTO",COMPRAS!F3:F183) -> 330 | M36: =L36/K36 -> 0.33
A37: PROTAMIN 25K | B37: 45524 | C37: 3 | D37: 25 | E37: =C37*D37 -> 75 | F37: 360 | G37: HF NOTA 43754 | H37: CONFINAMENTO/RAFAEL | J37: FERTIUM LIQUIDO 5L | K37: =SUMIF(COMPRAS!A3:A183,"FERTIUM LIQUIDO 5L",COMPRAS!E3:E183) -> 1000 | L37: =SUMIF(COMPRAS!A3:A183,"FERTIUM LIQUIDO 5L",COMPRAS!F3:F183) -> 217 | M37: =L37/K37 -> 0.217
A38: SULFATO DE MAGNESIO-KRISTA MGS 25K | B38: 45524 | C38: 3 | D38: 25 | E38: =C38*D38 -> 75 | F38: 234 | G38: HF NOTA 43754 | H38: CONFINAMENTO/RAFAEL | J38: FITILHO VIRGEM NOVELO NR 08 | K38: =SUMIF(COMPRAS!A3:A183,"FITILHO VIRGEM NOVELO NR 08",COMPRAS!E3:E183) -> 2 | L38: =SUMIF(COMPRAS!A4:A184,"FITILHO VIRGEM NOVELO NR 08",COMPRAS!F4:F184) -> 80 | M38: =L38/K38 -> 40
A39: TOPMIX 03-28-00 YARA 50K | B39: 45524 | C39: 6 | D39: 25 | E39: =C39*D39 -> 150 | F39: 1020 | G39: HF NOTA 43754 | H39: CONFINAMENTO/RAFAEL | J39: FRETE CAIXAS TOMATE | K39: =SUMIF(COMPRAS!A3:A183,"FRETE CAIXAS TOMATE",COMPRAS!E3:E183) -> 350 | L39: =SUMIF(COMPRAS!A3:A183,"FRETE CAIXAS TOMATE",COMPRAS!F3:F183) -> 825 | M39: =L39/K39 -> 2.3571429
A40: SEMENTE DE MILHO BIOMATRIX 3066 | B40: 45527 | C40: 4 | D40: 2 | E40: =C40*D40 -> 8 | F40: 540 | G40: TABELA CONFINAMENTO FINANCEIRO | J40: FTE 25K | K40: =SUMIF(COMPRAS!A3:A183,"FTE 25K",COMPRAS!E3:E183) -> 25 | L40: =SUMIF(COMPRAS!A3:A183,"FTE 25K",COMPRAS!F3:F183) -> 110 | M40: =L40/K40 -> 4.4
A41: AMISTAR TOP 1 L | B41: 45530 | C41: 1 | D41: 1000 | E41: =C41*D41 -> 1000 | F41: 205 | G41: HF NOTA 43845 | H41: CONFINAMENTO/RAFAEL | J41: FULVUMIM 5 LITROS | K41: =SUMIF(COMPRAS!A3:A183,"FULVUMIM 5 LITROS",COMPRAS!E3:E183) -> 70000 | L41: =SUMIF(COMPRAS!A3:A183,"FULVUMIM 5 LITROS",COMPRAS!F3:F183) -> 1810 | M41: =L41/K41 -> 0.025857143
A42: GLIBOR CA 5L | B42: 45530 | C42: 1 | D42: 5000 | E42: =C42*D42 -> 5000 | F42: 230 | G42: HF NOTA 43846 | H42: CONFINAMENTO/RAFAEL | J42: FYLLOTON 12X1 1 LITRO | K42: =SUMIF(COMPRAS!A3:A183,"FYLLOTON 12X1 1 LITRO",COMPRAS!E3:E183) -> 9000 | L42: =SUMIF(COMPRAS!A3:A183,"FYLLOTON 12X1 1 LITRO",COMPRAS!F3:F183) -> 605 | M42: =L42/K42 -> 0.067222222
A43: MICROCOMPLEX 1X25 25K | B43: 45530 | C43: 1 | D43: 25 | E43: =C43*D43 -> 25 | F43: 700 | G43: HF NOTA 43846 | H43: CONFINAMENTO/RAFAEL | J43: GLIBOR CA 5L | K43: =SUMIF(COMPRAS!A3:A183,"GLIBOR CA 5L",COMPRAS!E3:E183) -> 5000 | L43: =SUMIF(COMPRAS!A3:A183,"GLIBOR CA 5L",COMPRAS!F3:F183) -> 230 | M43: =L43/K43 -> 0.046
A44: MIRAVIS DUO 1 LITRO | B44: 45530 | C44: 1 | D44: 1000 | E44: =C44*D44 -> 1000 | F44: 260 | G44: HF NOTA 43845 | H44: CONFINAMENTO/RAFAEL | J44: GLIMAN 30 4X5 KG | K44: =SUMIF(COMPRAS!A3:A183,"GLIMAN 30 4X5 KG",COMPRAS!E3:E183) -> 5000 | L44: =SUMIF(COMPRAS!A3:A183,"GLIMAN 30 4X5 KG",COMPRAS!F3:F183) -> 200 | M44: =L44/K44 -> 0.04
A45: NUTRIGEMMA B ZN 5 LITROS | B45: 45530 | C45: 1 | D45: 5000 | E45: =C45*D45 -> 5000 | F45: 340 | G45: HF NOTA 43846 | H45: CONFINAMENTO/RAFAEL | J45: INTREPID240 SC -1 L | K45: =SUMIF(COMPRAS!A3:A183,"INTREPID240 SC -1 L",COMPRAS!E3:E183) -> 1000 | L45: =SUMIF(COMPRAS!A3:A183,"INTREPID240 SC -1 L",COMPRAS!F3:F183) -> 180 | M45: =L45/K45 -> 0.18
A46: RESTORER 5 LITROS | B46: 45530 | C46: 1 | D46: 5000 | E46: =C46*D46 -> 5000 | F46: 160 | G46: HF NOTA 43846 | H46: CONFINAMENTO/RAFAEL | J46: JOINER | K46: =SUMIF(COMPRAS!A3:A183,"JOINER",COMPRAS!E3:E183) -> 1000 | L46: =SUMIF(COMPRAS!A3:A183,"JOINER",COMPRAS!F3:F183) -> 2284 | M46: =L46/K46 -> 2.284
A47: PRIVILEGE 1L | B47: 45531 | C47: 1 | D47: 1000 | E47: =C47*D47 -> 1000 | F47: 160 | G47: UNIAGRO NOTA 62113 | J47: K BOMBER 56 8X2 5 KILOS | K47: =SUMIF(COMPRAS!A3:A183,"K BOMBER 56 8X2 5 KILOS ",COMPRAS!E3:E183) -> 5000 | L47: =SUMIF(COMPRAS!A3:A183,"K BOMBER 56 8X2 5 KILOS ",COMPRAS!F3:F183) -> 120 | M47: =L47/K47 -> 0.024
A48: N CALCIO CALCINIT YARA 15.5% 18CA 25K | B48: 45537 | C48: 4 | D48: 25 | E48: =C48*D48 -> 100 | F48: 360 | G48: HF NOTA 43948 | H48: RAMON GRUPO DIA 02-09-2025 | J48: KIT COSTAL AZR PLUS - EPI | K48: =SUMIF(COMPRAS!A3:A183,"KIT COSTAL AZR PLUS - EPI",COMPRAS!E3:E183) -> 1 | L48: =SUMIF(COMPRAS!A3:A183,"KIT COSTAL AZR PLUS - EPI",COMPRAS!F3:F183) -> 110 | M48: =L48/K48 -> 110
A49: AMPLIGO 250 ML | B49: 45538 | C49: 4 | D49: 250 | E49: =C49*D49 -> 1000 | F49: 390 | G49: HF NOTA 43995 | H49: CONFINAMENTO/FERNANDO | J49: KLORPAN 480 CE -1 LITRO | K49: =SUMIF(COMPRAS!A3:A183,"KLORPAN 480 CE -1 LITRO",COMPRAS!E3:E183) -> 21000 | L49: =SUMIF(COMPRAS!A3:A183,"KLORPAN 480 CE -1 LITRO",COMPRAS!F3:F183) -> 790 | M49: =L49/K49 -> 0.037619048
A50: AVATAR 1 L | B50: 45538 | C50: 1 | D50: 1000 | E50: =C50*D50 -> 1000 | F50: 375 | G50: UNIAGRO NOTA 62247 | J50: LANNATE | K50: =SUMIF(COMPRAS!A3:A183,"LANNATE",COMPRAS!E3:E183) -> 1000 | L50: =SUMIF(COMPRAS!A3:A183,"LANNATE",COMPRAS!F3:F183) -> 50 | M50: =L50/K50 -> 0.05
A51: N CALCIO CALCINIT YARA 15.5% 18CA 25K | B51: 45540 | C51: 3 | D51: 25 | E51: =C51*D51 -> 75 | F51: 270 | G51: HF NOTA 44026 | H51: CONFINAMENTO/FERNANDO | J51: MASTER 20-20-20 25 KG | K51: =SUMIF(COMPRAS!A3:A183,"MASTER 20-20-20 25 KG",COMPRAS!E3:E183) -> 50 | L51: =SUMIF(COMPRAS!A3:A183,"MASTER 20-20-20 25 KG",COMPRAS!F3:F183) -> 580 | M51: =L51/K51 -> 11.6
A52: SEMENTE MILHO HIB FEROZ SYN8A98 TL TG FORT VIP TURBO | B52: 45540 | C52: 3 | D52: 1000 | E52: =C52*D52 -> 3000 | F52: 1650 | G52: HF NOTA 44027 | H52: SABER QUEM FOI | J52: MAXIHUN 5 L | K52: =SUMIF(COMPRAS!A3:A183,"MAXIHUN 5 L",COMPRAS!E3:E183) -> 5000 | L52: =SUMIF(COMPRAS!A3:A183,"MAXIHUN 5 L",COMPRAS!F3:F183) -> 115 | M52: =L52/K52 -> 0.023
A53: SEMENTE MILHO HIB FEROZ SYN8A98 TL TG VIP FORTENZA | B53: 45540 | C53: 2 | D53: 1000 | E53: =C53*D53 -> 2000 | F53: 1000 | G53: HF NOTA 44027 | H53: SABER QUEM FOI | J53: MICROCOMPLEX 1X25 25K | K53: =SUMIF(COMPRAS!A3:A183,"MICROCOMPLEX 1X25 25K",COMPRAS!E3:E183) -> 25 | L53: =SUMIF(COMPRAS!A3:A183,"MICROCOMPLEX 1X25 25K",COMPRAS!F3:F183) -> 700 | M53: =L53/K53 -> 28
A54: SULFATO DE MAGNESIO-KRISTA MGS 25K | B54: 45540 | C54: 1 | D54: 25 | E54: =C54*D54 -> 25 | F54: 90 | G54: HF NOTA 44026 | H54: CONFINAMENTO/FERNANDO | J54: MINECTO PRO 12X1LT | K54: =SUMIF(COMPRAS!A3:A183,"MINECTO PRO 12X1LT",COMPRAS!E3:E183) -> 1000 | L54: =SUMIF(COMPRAS!A3:A183,"MINECTO PRO 12X1LT",COMPRAS!F3:F183) -> 230 | M54: =L54/K54 -> 0.23
A55: CAL SUPER 5 LITROS | B55: 45545 | C55: 1 | D55: 5000 | E55: =C55*D55 -> 5000 | F55: 220 | G55: UNIAGRO NOTA 62314 | J55: MIRAVIS DUO 1 LITRO | K55: =SUMIF(COMPRAS!A3:A183,"MIRAVIS DUO 1 LITRO",COMPRAS!E3:E183) -> 1000 | L55: =SUMIF(COMPRAS!A3:A183,"MIRAVIS DUO 1 LITRO",COMPRAS!F3:F183) -> 260 | M55: =L55/K55 -> 0.26
A56: PIRATE 1 LITRO | B56: 45545 | C56: 1 | D56: 1000 | E56: =C56*D56 -> 1000 | F56: 120 | G56: UNIAGRO NOTA 62314 | J56: MULTICARE 1L | K56: =SUMIF(COMPRAS!A3:A183,"MULTICARE 1L",COMPRAS!E3:E183) -> 1000 | L56: =SUMIF(COMPRAS!A3:A183,"MULTICARE 1L",COMPRAS!F3:F183) -> 52 | M56: =L56/K56 -> 0.052
A57: DRIPSOL MULTIPROPOSITO-18-18-18 25 K | B57: 45548 | C57: 7 | D57: 25 | E57: =C57*D57 -> 175 | F57: 1855 | G57: HF NOTA 44113 | H57: CONFINAMENTO/FERNANDO | J57: N CALCIO CALCINIT YARA 15.5% 18CA 25K | K57: =SUMIF(COMPRAS!A3:A183,"N CALCIO CALCINIT YARA 15.5% 18CA 25K",COMPRAS!E3:E183) -> 675 | L57: =SUMIF(COMPRAS!A3:A183,"N CALCIO CALCINIT YARA 15.5% 18CA 25K",COMPRAS!F3:F183) -> 2276 | M57: =L57/K57 -> 3.3718519
A58: FULVUMIM 5 LITROS | B58: 45548 | C58: 4 | D58: 5000 | E58: =C58*D58 -> 20000 | F58: 440 | G58: HF NOTA 44113 | H58: CONFINAMENTO/FERNANDO | J58: NITRATO DE POTASSIO 12% N 45% K2O 2%S 25 K | K58: =SUMIF(COMPRAS!A3:A183,"NITRATO DE POTASSIO 12% N 45% K2O 2%S 25 K",COMPRAS!E3:E183) -> 100 | L58: =SUMIF(COMPRAS!A3:A183,"NITRATO DE POTASSIO 12% N 45% K2O 2%S 25 K",COMPRAS!F3:F183) -> 800 | M58: =L58/K58 -> 8
A59: PHOSIFK CU4 1 LITRO | B59: 45548 | C59: 5 | D59: 1000 | E59: =C59*D59 -> 5000 | F59: 490 | G59: HF NOTA 44113 | H59: CONFINAMENTO/FERNANDO | J59: NITRATO POTASSIO YARA TERA K 13-00-43 | K59: =SUMIF(COMPRAS!A3:A183,"NITRATO POTASSIO YARA TERA K 13-00-43",COMPRAS!E3:E183) -> 275 | L59: =SUMIF(COMPRAS!A3:A183,"NITRATO POTASSIO YARA TERA K 13-00-43",COMPRAS!F3:F183) -> 2346 | M59: =L59/K59 -> 8.5309091
A60: RESTORER 5 LITROS | B60: 45548 | C60: 2 | D60: 5000 | E60: =C60*D60 -> 10000 | F60: 320 | G60: HF NOTA 44113 | H60: CONFINAMENTO/FERNANDO | J60: NITROCAM 12X1 LT | K60: =SUMIF(COMPRAS!A3:A183,"NITROCAM 12X1 LT",COMPRAS!E3:E183) -> 1000 | L60: =SUMIF(COMPRAS!A3:A183,"NITROCAM 12X1 LT",COMPRAS!F3:F183) -> 48 | M60: =L60/K60 -> 0.048
A61: FYLLOTON 12X1 1 LITRO | B61: 45551 | C61: 5 | D61: 1000 | E61: =C61*D61 -> 5000 | F61: 325 | G61: HF NOTA 44126 | H61: CONFINAMENTO/RAFAEL | J61: NKP | K61: =SUMIF(COMPRAS!A3:A183,"NKP",COMPRAS!E3:E183) -> 104 | L61: =SUMIF(COMPRAS!A3:A183,"NKP",COMPRAS!F3:F183) -> 436.8 | M61: =L61/K61 -> 4.2
A62: DRIPSOL MULTIPROPOSITO-18-18-18 25 K | B62: 45552 | C62: 1 | D62: 25 | E62: =C62*D62 -> 25 | F62: 250 | G62: HF NOTA 44185 | H62: RAMON | J62: NUPRID
A63: DRIPSOL CRESCIMENTO 24-10-10 25 KG | B63: 45555 | C63: 1 | D63: 25 | E63: =C63*D63 -> 25 | F63: 265 | G63: HF NOTA 44234 | H63: CONFINAMENTO/RAFAEL | J63: NUTRIGEMMA B ZN 5 LITROS | K63: =SUMIF(COMPRAS!A3:A183,"NUTRIGEMMA B ZN 5 LITROS",COMPRAS!E3:E183) -> 5000 | L63: =SUMIF(COMPRAS!A3:A183,"NUTRIGEMMA B ZN 5 LITROS",COMPRAS!F3:F183) -> 340 | M63: =L63/K63 -> 0.068
A64: GLIMAN 30 4X5 KG | B64: 45555 | C64: 1 | D64: 5000 | E64: =C64*D64 -> 5000 | F64: 200 | G64: HF NOTA 44234 | H64: CONFINAMENTO/RAFAEL | J64: NUTRISYSTEM INICIAL 42 06.30.06 25 K | K64: =SUMIF(COMPRAS!A3:A183,"NUTRISYSTEM INICIAL 42 06.30.06 25 K",COMPRAS!E3:E183) -> 950 | L64: =SUMIF(COMPRAS!A3:A183,"NUTRISYSTEM INICIAL 42 06.30.06 25 K",COMPRAS!F3:F183) -> 4370 | M64: =L64/K64 -> 4.6
A65: N CALCIO CALCINIT YARA 15.5% 18CA 25K | B65: 45555 | C65: 2 | D65: 25 | E65: =C65*D65 -> 50 | F65: 180 | G65: HF NOTA 44234 | H65: CONFINAMENTO/RAFAEL | J65: PADRON - 1 LITRO | K65: =SUMIF(COMPRAS!A3:A183,"PADRON - 1 LITRO",COMPRAS!E3:E183) -> 2000 | L65: =SUMIF(COMPRAS!A3:A183,"PADRON - 1 LITRO",COMPRAS!F3:F183) -> 180 | M65: =L65/K65 -> 0.09
A66: NITROCAM 12X1 LT | B66: 45555 | C66: 1 | D66: 1000 | E66: =C66*D66 -> 1000 | F66: 48 | G66: HF NOTA 44234 | H66: CONFINAMENTO/RAFAEL | J66: PAGAMENTO FEITA DE MUDAS 2º PLANTIO | K66: =SUMIF(COMPRAS!A3:A183,"PAGAMENTO FEITA DE MUDAS 2º PLANTIO",COMPRAS!E3:E183) -> 12000 | L66: =SUMIF(COMPRAS!A3:A183,"PAGAMENTO FEITA DE MUDAS 2º PLANTIO",COMPRAS!F3:F183) -> 2400 | M66: =L66/K66 -> 0.2
A67: RIDOMIL GOLD MZ 680 WG 12X1 KG | B67: 45555 | C67: 1 | D67: 1000 | E67: =C67*D67 -> 1000 | F67: 156 | G67: HF NOTA 44234 | H67: CONFINAMENTO/RAFAEL | J67: PHOSIFK CU4 1 LITRO | K67: =SUMIF(COMPRAS!A3:A183,"PHOSIFK CU4 1 LITRO",COMPRAS!E3:E183) -> 5000 | L67: =SUMIF(COMPRAS!A3:A183,"PHOSIFK CU4 1 LITRO",COMPRAS!F3:F183) -> 490 | M67: =L67/K67 -> 0.098
A68: SPRAY DUNGER 20X1KG | B68: 45555 | C68: 1 | D68: 1000 | E68: =C68*D68 -> 1000 | F68: 80 | G68: HF NOTA 44234 | H68: CONFINAMENTO/RAFAEL | J68: PIRATE 1 LITRO | K68: =SUMIF(COMPRAS!A3:A183,"PIRATE 1 LITRO",COMPRAS!E3:E183) -> 3000 | L68: =SUMIF(COMPRAS!A3:A183,"PIRATE 1 LITRO",COMPRAS!F3:F183) -> 365 | M68: =L68/K68 -> 0.12166667
A69: SULFATO DE MAGNESIO-KRISTA MGS 25K | B69: 45555 | D69: 25 | E69: =C69*D69 -> 0 | G69: HF NOTA 44234 | H69: CONFINAMENTO/RAFAEL | J69: PLATINUM NEO - GL 5 LITROS | K69: =SUMIF(COMPRAS!A3:A183,"PLATINUM NEO - GL 5 LITROS",COMPRAS!E3:E183) -> 15000 | L69: =SUMIF(COMPRAS!A3:A183,"PLATINUM NEO - GL 5 LITROS",COMPRAS!F3:F183) -> 2600 | M69: =L69/K69 -> 0.17333333
A70: N CALCIO CALCINIT YARA 15.5% 18CA 25K | B70: 45562 | C70: 6 | D70: 25 | E70: =C70*D70 -> 150 | F70: 510 | G70: HF NOTA 44323 | H70: RAMON | J70: POQUER 4X5 LITROS | K70: =SUMIF(COMPRAS!A3:A183,"POQUER 4X5 LITROS",COMPRAS!E3:E183) -> 5000 | L70: =SUMIF(COMPRAS!A3:A183,"POQUER 4X5 LITROS",COMPRAS!F3:F183) -> 163 | M70: =L70/K70 -> 0.0326
A71: NITRATO DE POTASSIO 12% N 45% K2O 2%S 25 K | B71: 45562 | C71: 4 | D71: 25 | E71: =C71*D71 -> 100 | F71: 800 | G71: HF NOTA 44323 | H71: RAMON | J71: PRIMOLEO 1X20LT | K71: =SUMIF(COMPRAS!A3:A183,"PRIMOLEO 1X20LT",COMPRAS!E3:E183) -> 20000 | L71: =SUMIF(COMPRAS!A3:A183,"PRIMOLEO 1X20LT",COMPRAS!F3:F183) -> 460 | M71: =L71/K71 -> 0.023
A72: DRIPSOL MULTIPROPOSITO-18-18-18 25 K | B72: 45567 | C72: 2 | D72: 25 | E72: =C72*D72 -> 50 | F72: 470 | G72: HF NOTA 44409 | H72: RAMON | J72: PRIVILEGE 1L | K72: =SUMIF(COMPRAS!A3:A183,"PRIVILEGE 1L",COMPRAS!E3:E183) -> 1000 | L72: =SUMIF(COMPRAS!A3:A183,"PRIVILEGE 1L",COMPRAS!F3:F183) -> 160 | M72: =L72/K72 -> 0.16
A73: DRIPSOL PRODUÇÃO 12-06-40 25K | B73: 45567 | C73: 1 | D73: 25 | E73: =C73*D73 -> 25 | F73: 275 | G73: HF NOTA 44409 | H73: CONFINAMENTO/JEAN 360,00 RAMON 470,00 | J73: PROGIBB 400 - PCT 2,5 GR | K73: =SUMIF(COMPRAS!A3:A183,"PROGIBB 400 - PCT 2,5 GR",COMPRAS!E3:E183) -> 40 | L73: =SUMIF(COMPRAS!A3:A183,"PROGIBB 400 - PCT 2,5 GR",COMPRAS!F3:F183) -> 240 | M73: =L73/K73 -> 6
A74: SULFATO DE MAGNESIO-KRISTA MGS 25K | B74: 45567 | C74: 1 | D74: 25 | E74: =C74*D74 -> 25 | F74: 75 | G74: HF NOTA 44409 | H74: CONFINAMENTO/JEAN 360,00 RAMON 470,00 | J74: PROTAMIN 25K | K74: =SUMIF(COMPRAS!A3:A183,"PROTAMIN 25K",COMPRAS!E3:E183) -> 100 | L74: =SUMIF(COMPRAS!A3:A183,"PROTAMIN 25K",COMPRAS!F3:F183) -> 490 | M74: =L74/K74 -> 4.9
A75: DISPAROULTRA-S - GL DE 5 LITROS | B75: 45572 | C75: 1 | D75: 5000 | E75: =C75*D75 -> 5000 | F75: 140 | G75: UNIAGRO NOTA 62656 | H75: WENDES | J75: QUIMIFOL CALCIO E BORO II- BD 20 L | K75: =SUMIF(COMPRAS!A3:A183,"QUIMIFOL CALCIO E BORO II- BD 20 L",COMPRAS!E3:E183) -> 20000 | L75: =SUMIF(COMPRAS!A3:A183,"QUIMIFOL CALCIO E BORO II- BD 20 L",COMPRAS!F3:F183) -> 470 | M75: =L75/K75 -> 0.0235
A76: N CALCIO CALCINIT YARA 15.5% 18CA 25K | B76: 45572 | C76: 4 | D76: 25 | E76: =C76*D76 -> 100 | F76: 296 | G76: HF NOTA 44436 | H76: CONFINAMENTO/FERNANDO | J76: QUIMIFOL IMPACTO - 1 LITRO | K76: =SUMIF(COMPRAS!A3:A183,"QUIMIFOL IMPACTO - 1 LITRO",COMPRAS!E3:E183) -> 1000 | L76: =SUMIF(COMPRAS!A3:A183,"QUIMIFOL IMPACTO - 1 LITRO",COMPRAS!F3:F183) -> 220 | M76: =L76/K76 -> 0.22
A77: ROUNDUP ORIGINAL MAIS - GL DE 5 L | B77: 45572 | C77: 1 | D77: 5000 | E77: =C77*D77 -> 5000 | F77: 160 | G77: UNIAGRO NOTA 62656 | H77: WENDES | J77: QUIMIFOL P30W- GL 5 LITROS | K77: =SUMIF(COMPRAS!A3:A183,"QUIMIFOL P30W- GL 5 LITROS",COMPRAS!E3:E183) -> 5000 | L77: =SUMIF(COMPRAS!A3:A183,"QUIMIFOL P30W- GL 5 LITROS",COMPRAS!F3:F183) -> 180 | M77: =L77/K77 -> 0.036
A78: YARAREGA 18-05-18 25 K | B78: 45572 | C78: 2 | D78: 25 | E78: =C78*D78 -> 50 | F78: 344 | G78: HF NOTA 44436 | H78: CONFINAMENTO/FERNANDO | J78: QUIMIFOL PERSIST- 1 LITRO | K78: =SUMIF(COMPRAS!A3:A183,"QUIMIFOL PERSIST- 1 LITRO",COMPRAS!E3:E183) -> 3000 | L78: =SUMIF(COMPRAS!A3:A183,"QUIMIFOL PERSIST- 1 LITRO",COMPRAS!F3:F183) -> 110 | M78: =L78/K78 -> 0.036666667
A79: ACIDO BORICO SACO 25K | B79: 45578 | C79: 1 | D79: 25 | E79: =C79*D79 -> 25 | F79: 255 | G79: TABELA ANTIGA DO TOMATE COMPRAS RAMON | J79: QUIMIFOL PHFOS - 1 LITRO | K79: =SUMIF(COMPRAS!A3:A183,"QUIMIFOL PHFOS - 1 LITRO",COMPRAS!E3:E183) -> 1000 | L79: =SUMIF(COMPRAS!A3:A183,"QUIMIFOL PHFOS - 1 LITRO",COMPRAS!F3:F183) -> 60 | M79: =L79/K79 -> 0.06
A80: NITRATO POTASSIO YARA TERA K 13-00-43 | B80: 45580 | C80: 2 | D80: 25 | E80: =C80*D80 -> 50 | F80: 420 | G80: HF NOTA 44557 | H80: CONFINAMENTO/FERNANDO | J80: QUIMIFOL S450 - GL 5 LITROS | K80: =SUMIF(COMPRAS!A3:A183,"QUIMIFOL S450 - GL 5 LITROS",COMPRAS!E3:E183) -> 5000 | L80: =SUMIF(COMPRAS!A3:A183,"QUIMIFOL S450 - GL 5 LITROS",COMPRAS!F3:F183) -> 210 | M80: =L80/K80 -> 0.042
A81: YARAREGA 18-05-18 25 K | B81: 45580 | C81: 2 | D81: 25 | E81: =C81*D81 -> 50 | F81: 340 | G81: HF NOTA 44557 | H81: RAMON | J81: QUIMIORGEN 20 N - GL DE 5 LITROS | K81: =SUMIF(COMPRAS!A3:A183,"QUIMIORGEN 20 N - GL DE 5 LITROS",COMPRAS!E3:E183) -> 10000 | L81: =SUMIF(COMPRAS!A3:A183,"QUIMIORGEN 20 N - GL DE 5 LITROS",COMPRAS!F3:F183) -> 220 | M81: =L81/K81 -> 0.022
A82: DOMINUM XT-S - GL 5 LITROS | B82: 45583 | C82: 1 | D82: 5000 | E82: =C82*D82 -> 5000 | F82: 640 | G82: UNIAGRO NOTA 62831 | J82: RAPEL PCT- 3 KG | K82: =SUMIF(COMPRAS!A3:A183,"RAPEL PCT- 3 KG",COMPRAS!E3:E183) -> 6000 | L82: =SUMIF(COMPRAS!A3:A183,"RAPEL PCT- 3 KG",COMPRAS!F3:F183) -> 340 | M82: =L82/K82 -> 0.056666667
A83: KIT COSTAL AZR PLUS - EPI | B83: 45583 | C83: 1 | D83: 1 | E83: =C83*D83 -> 1 | F83: 110 | G83: UNIAGRO NOTA 62833 | J83: RESTORER 5 LITROS | K83: =SUMIF(COMPRAS!A3:A183,"RESTORER 5 LITROS",COMPRAS!E3:E183) -> 45000 | L83: =SUMIF(COMPRAS!A3:A183,"RESTORER 5 LITROS",COMPRAS!F3:F183) -> 1490 | M83: =L83/K83 -> 0.033111111
A84: PIRATE 1 LITRO | B84: 45583 | C84: 1 | D84: 1000 | E84: =C84*D84 -> 1000 | F84: 120 | G84: UNIAGRO NOTA 62832 | J84: RIDOMIL GOLD BRAVO 1 LITRO | K84: =SUMIF(COMPRAS!A3:A183,"RIDOMIL GOLD BRAVO 1 LITRO",COMPRAS!E3:E183) -> 1000 | L84: =SUMIF(COMPRAS!A3:A183,"RIDOMIL GOLD BRAVO 1 LITRO",COMPRAS!F3:F183) -> 120 | M84: =L84/K84 -> 0.12
A85: QUIMIFOL PERSIST- 1 LITRO | B85: 45583 | C85: 2 | D85: 1000 | E85: =C85*D85 -> 2000 | F85: 70 | G85: UNIAGRO NOTA 62831 | J85: RIDOMIL GOLD MZ 680 WG 12X1 KG | K85: =SUMIF(COMPRAS!A3:A183,"RIDOMIL GOLD MZ 680 WG 12X1 KG",COMPRAS!E3:E183) -> 1000 | L85: =SUMIF(COMPRAS!A3:A183,"RIDOMIL GOLD MZ 680 WG 12X1 KG",COMPRAS!F3:F183) -> 156 | M85: =L85/K85 -> 0.156
A86: QUIMIORGEN 20 N - GL DE 5 LITROS | B86: 45583 | C86: 2 | D86: 5000 | E86: =C86*D86 -> 10000 | F86: 220 | G86: UNIAGRO NOTA 62831 | J86: RIZAMMINA 42 OS 8X2 5 KILOS | K86: =SUMIF(COMPRAS!A3:A183,"RIZAMMINA 42 OS 8X2 5 KILOS",COMPRAS!E3:E183) -> 5000 | L86: =SUMIF(COMPRAS!A3:A183,"RIZAMMINA 42 OS 8X2 5 KILOS",COMPRAS!F3:F183) -> 170 | M86: =L86/K86 -> 0.034
A87: TORDONULTRA-S - BD 20 LITROS | B87: 45583 | C87: 1 | D87: 20000 | E87: =C87*D87 -> 20000 | F87: 1100 | G87: UNIAGRO NOTA 62831 | J87: ROUNDUP ORIGINAL MAIS - GL DE 5 L | K87: =SUMIF(COMPRAS!A3:A183,"ROUNDUP ORIGINAL MAIS - GL DE 5 L",COMPRAS!E3:E183) -> 20000 | L87: =SUMIF(COMPRAS!A3:A183,"ROUNDUP ORIGINAL MAIS - GL DE 5 L",COMPRAS!F3:F183) -> 775 | M87: =L87/K87 -> 0.03875
A88: DRIPSOL MULTIPROPOSITO-18-18-18 25 K | B88: 45584 | C88: 1 | D88: 25 | E88: =C88*D88 -> 25 | F88: 228 | G88: HF NOTA 44610 | H88: CONFINAMENTO/RAFAEL | J88: SCORE 250 EC - 1 LITRO | K88: =SUMIF(COMPRAS!A3:A183,"SCORE 250 EC - 1 LITRO",COMPRAS!E3:E183) -> 1000 | L88: =SUMIF(COMPRAS!A3:A183,"SCORE 250 EC - 1 LITRO",COMPRAS!F3:F183) -> 95 | M88: =L88/K88 -> 0.095
A89: N CALCIO CALCINIT YARA 15.5% 18CA 25K | B89: 45584 | C89: 3 | D89: 25 | E89: =C89*D89 -> 75 | F89: 210 | G89: HF NOTA 44610 | H89: CONFINAMENTO/RAFAEL | J89: SEMENTE DE MILHO BIOMATRIX 3066 | K89: =SUMIF(COMPRAS!A3:A183,"SEMENTE DE MILHO BIOMATRIX 3066",COMPRAS!E3:E183) -> 8 | L89: =SUMIF(COMPRAS!A3:A183,"SEMENTE DE MILHO BIOMATRIX 3066",COMPRAS!F3:F183) -> 540 | M89: =L89/K89 -> 67.5
A90: NITRATO POTASSIO YARA TERA K 13-00-43 | B90: 45584 | C90: 3 | D90: 25 | E90: =C90*D90 -> 75 | F90: 642 | G90: HF NOTA 44610 | H90: CONFINAMENTO/RAFAEL | J90: SEMENTE MELANCIA
A91: YARAREGA 18-05-18 25 K | B91: 45584 | C91: 8 | D91: 25 | E91: =C91*D91 -> 200 | F91: 1360 | G91: HF NOTA 44610 | H91: CONFINAMENTO/RAFAEL | J91: SEMENTE MELANCIA CRIMSON SELE | K91: =SUMIF(COMPRAS!A3:A183,"SEMENTE MELANCIA CRIMSON SELE",COMPRAS!E3:E183) -> 1000 | L91: =SUMIF(COMPRAS!A3:A183,"SEMENTE MELANCIA CRIMSON SELE",COMPRAS!F3:F183) -> 290 | M91: =L91/K91 -> 0.29
A92: DELEGATE(TM) - FR 120 GR | B92: 45587 | C92: 1 | D92: 120 | E92: =C92*D92 -> 120 | F92: 330 | G92: HF NOTA 62937 | H92: CONFINAMENTO (FALTA NOTA ) | J92: SEMENTE MELANCIA H MANCHESTER | K92: =SUMIF(COMPRAS!A3:A183,"SEMENTE MELANCIA H MANCHESTER",COMPRAS!E3:E183) -> 2000 | L92: =SUMIF(COMPRAS!A3:A183,"SEMENTE MELANCIA H MANCHESTER",COMPRAS!F3:F183) -> 860 | M92: =L92/K92 -> 0.43
A93: DELEGATE(TM) - FR 120 GR | B93: 45587 | C93: 1 | D93: 120 | E93: =C93*D93 -> 120 | F93: 330 | G93: UNIAGRO NOTA 62937 | J93: SEMENTE MILHO HIB FEROZ SYN8A98 TL TG FORT VIP TURBO | K93: =SUMIF(COMPRAS!A3:A183,"SEMENTE MILHO HIB FEROZ SYN8A98 TL TG FORT VIP TURBO",COMPRAS!E3:E183) -> 3000 | L93: =SUMIF(COMPRAS!A3:A183,"SEMENTE MILHO HIB FEROZ SYN8A98 TL TG FORT VIP TURBO",COMPRAS!F3:F183) -> 1650 | M93: =L93/K93 -> 0.55
A94: FULVUMIM 5 LITROS | B94: 45588 | C94: 2 | D94: 5000 | E94: =C94*D94 -> 10000 | F94: 220 | G94: HF NOTA 44696 | H94: CONFINAMENTO/FERNANDO | J94: SEMENTE MILHO HIB FEROZ SYN8A98 TL TG VIP FORTENZA | K94: =SUMIF(COMPRAS!A3:A183,"SEMENTE MILHO HIB FEROZ SYN8A98 TL TG VIP FORTENZA",COMPRAS!E3:E183) -> 2000 | L94: =SUMIF(COMPRAS!A3:A183,"SEMENTE MILHO HIB FEROZ SYN8A98 TL TG VIP FORTENZA",COMPRAS!F3:F183) -> 1000 | M94: =L94/K94 -> 0.5
A95: K BOMBER 56 8X2 5 KILOS | B95: 45588 | C95: 1 | D95: 5000 | E95: =C95*D95 -> 5000 | F95: 120 | G95: HF NOTA 44696 | H95: CONFINAMENTO/FERNANDO | J95: SEMENTE TOMATE | K95: =SUMIF(COMPRAS!A3:A183,"SEMENTE TOMATE ",COMPRAS!E3:E183) -> 5000 | L95: =SUMIF(COMPRAS!A3:A183,"SEMENTE TOMATE ",COMPRAS!F3:F183) -> 2700 | M95: =L95/K95 -> 0.54
A96: RIZAMMINA 42 OS 8X2 5 KILOS | B96: 45588 | C96: 1 | D96: 5000 | E96: =C96*D96 -> 5000 | F96: 170 | G96: HF NOTA 44696 | H96: CONFINAMENTO/FERNANDO | J96: SEMENTE TOMATE COLT 1000 SEMENTES | K96: =SUMIF(COMPRAS!A3:A183,"SEMENTE TOMATE COLT 1000 SEMENTES",COMPRAS!E3:E183) -> 12000 | L96: =SUMIF(COMPRAS!A3:A183,"SEMENTE TOMATE COLT 1000 SEMENTES",COMPRAS!F3:F183) -> 6840 | M96: =L96/K96 -> 0.57
A97: SPRAY DUNGER 20X1KG | B97: 45588 | C97: 1 | D97: 1000 | E97: =C97*D97 -> 1000 | F97: 80 | G97: HF NOTA 44696 | H97: CONFINAMENTO/FERNANDO | J97: SENCOR 480 SC- 1 LITRO | K97: =SUMIF(COMPRAS!A3:A183,"SENCOR 480 SC- 1 LITRO",COMPRAS!E3:E183) -> 1000 | L97: =SUMIF(COMPRAS!A3:A183,"SENCOR 480 SC- 1 LITRO",COMPRAS!F3:F183) -> 140 | M97: =L97/K97 -> 0.14
A98: YARAREGA 18-05-18 25 K | B98: 45588 | C98: 7 | D98: 25 | E98: =C98*D98 -> 175 | F98: 1190 | G98: HF NOTA 44696 | H98: CONFINAMENTO/FERNANDO | J98: SPRAY DUNGER 20X1KG | K98: =SUMIF(COMPRAS!A3:A183,"SPRAY DUNGER 20X1KG",COMPRAS!E3:E183) -> 2000 | L98: =SUMIF(COMPRAS!A3:A183,"SPRAY DUNGER 20X1KG",COMPRAS!F3:F183) -> 160 | M98: =L98/K98 -> 0.08
A99: SEMENTE TOMATE COLT 1000 SEMENTES | B99: 45589 | C99: 12 | D99: 1000 | E99: =C99*D99 -> 12000 | F99: 6840 | G99: HF NOTA 44714 | H99: SEMENTE TOMATE 2 PLANTIO | J99: SPRINT ALGA TS 12X1LT | K99: =SUMIF(COMPRAS!A3:A183,"SPRINT ALGA TS 12X1LT",COMPRAS!E3:E183) -> 1000 | L99: =SUMIF(COMPRAS!A3:A183,"SPRINT ALGA TS 12X1LT",COMPRAS!F3:F183) -> 200 | M99: =L99/K99 -> 0.2
A100: MINECTO PRO 12X1LT | B100: 45595 | C100: 1 | D100: 1000 | E100: =C100*D100 -> 1000 | F100: 230 | G100: HF NOTA 44827 | H100: CONFINAMENTO/FERNANDO | J100: SUFATO DE AMONIO | K100: =SUMIF(COMPRAS!A3:A183,"SUFATO DE AMONIO",COMPRAS!E3:E183) -> 750 | L100: =SUMIF(COMPRAS!A3:A183,"SUFATO DE AMONIO",COMPRAS!F3:F183) -> 1800 | M100: =L100/K100 -> 2.4
...

Sheet FECHAMENTOS
A1: CONFINAMENTO-MILHO | D1: CONFINAMENTO-TOMATE
A2: DESCRIÇÃO | B2: VALOR | D2: DESCRIÇÃO | E2: VALOR
A3: IRRIGAÇÃO | B3: ='CONFINAMENTO-MILHO'!B106 -> 1583.88 | D3: IRRIGAÇÃO | E3: =TOMATE!B106 -> 0
A4: ADUBOS | B4: ='CONFINAMENTO-MILHO'!K120 -> 2126.948 | D4: ADUBOS | E4: =TOMATE!K120 -> 7424.0025
A5: DIARIAS DE TRABALHADOR | B5: ='CONFINAMENTO-MILHO'!Q35 -> 4103.2 | D5: DIARIAS DE TRABALHADOR | E5: =TOMATE!Q35 -> 3372.5
A6: MAQUINA DE VENENO | B6: ='CONFINAMENTO-MILHO'!W35 -> 240 | D6: MAQUINA DE VENENO | E6: =TOMATE!W35 -> 645
A11: TOTAL | B11: =SUM(B3:B10) -> 8054.028 | D11: TOTAL | E11: =SUM(E3:E10) -> 11441.503
